{"v":"5.5.7","meta":{"g":"LottieFiles AE 0.1.20","a":"","k":"","d":"","tc":""},"fr":30,"ip":0,"op":60,"w":356,"h":311,"nm":"Frame 159","ddd":0,"assets":[],"layers":[{"ddd":0,"ind":1,"ty":4,"nm":"Ellipse 54","sr":1,"ks":{"o":{"a":0,"k":100,"ix":11},"r":{"a":0,"k":0,"ix":10},"p":{"a":0,"k":[317,61,0],"ix":2},"a":{"a":0,"k":[0,0,0],"ix":1},"s":{"a":1,"k":[{"i":{"x":[0.667,0.667,0.667],"y":[1,1,1]},"o":{"x":[0.333,0.333,0.333],"y":[0,0,0]},"t":28,"s":[0,0,100]},{"t":36,"s":[100,100,100]}],"ix":6}},"ao":0,"shapes":[{"ty":"gr","it":[{"ind":0,"ty":"sh","ix":1,"ks":{"a":0,"k":{"i":[[-4.971,0],[0,4.971],[4.971,0],[0,-4.971]],"o":[[4.971,0],[0,-4.971],[-4.971,0],[0,4.971]],"v":[[0,9],[9,0],[0,-9],[-9,0]],"c":true},"ix":2},"nm":"Path 1","mn":"ADBE Vector Shape - Group","hd":false},{"ty":"fl","c":{"a":0,"k":[0.568627476692,0.784313738346,0.764705896378,1],"ix":4},"o":{"a":0,"k":100,"ix":5},"r":1,"bm":0,"nm":"Fill 1","mn":"ADBE Vector Graphic - Fill","hd":false},{"ty":"tr","p":{"a":0,"k":[0,0],"ix":2},"a":{"a":0,"k":[0,0],"ix":1},"s":{"a":0,"k":[100,100],"ix":3},"r":{"a":0,"k":0,"ix":6},"o":{"a":0,"k":100,"ix":7},"sk":{"a":0,"k":0,"ix":4},"sa":{"a":0,"k":0,"ix":5},"nm":"Transform"}],"nm":"Ellipse 53","np":2,"cix":2,"bm":0,"ix":1,"mn":"ADBE Vector Group","hd":false}],"ip":0,"op":60,"st":0,"bm":0},{"ddd":0,"ind":2,"ty":4,"nm":"Ellipse 53","sr":1,"ks":{"o":{"a":0,"k":100,"ix":11},"r":{"a":0,"k":0,"ix":10},"p":{"a":0,"k":[61,276,0],"ix":2},"a":{"a":0,"k":[0,0,0],"ix":1},"s":{"a":1,"k":[{"i":{"x":[0.667,0.667,0.667],"y":[1,1,1]},"o":{"x":[0.333,0.333,0.333],"y":[0,0,0]},"t":0,"s":[0,0,100]},{"t":11,"s":[100,100,100]}],"ix":6}},"ao":0,"shapes":[{"ty":"gr","it":[{"ind":0,"ty":"sh","ix":1,"ks":{"a":0,"k":{"i":[[-4.971,0],[0,4.971],[4.971,0],[0,-4.971]],"o":[[4.971,0],[0,-4.971],[-4.971,0],[0,4.971]],"v":[[0,9],[9,0],[0,-9],[-9,0]],"c":true},"ix":2},"nm":"Path 1","mn":"ADBE Vector Shape - Group","hd":false},{"ty":"fl","c":{"a":0,"k":[0.568627476692,0.784313738346,0.764705896378,1],"ix":4},"o":{"a":0,"k":100,"ix":5},"r":1,"bm":0,"nm":"Fill 1","mn":"ADBE Vector Graphic - Fill","hd":false},{"ty":"tr","p":{"a":0,"k":[0,0],"ix":2},"a":{"a":0,"k":[0,0],"ix":1},"s":{"a":0,"k":[100,100],"ix":3},"r":{"a":0,"k":0,"ix":6},"o":{"a":0,"k":100,"ix":7},"sk":{"a":0,"k":0,"ix":4},"sa":{"a":0,"k":0,"ix":5},"nm":"Transform"}],"nm":"Ellipse 53","np":2,"cix":2,"bm":0,"ix":1,"mn":"ADBE Vector Group","hd":false}],"ip":0,"op":60,"st":0,"bm":0},{"ddd":0,"ind":3,"ty":4,"nm":"Shape Layer 1","sr":1,"ks":{"o":{"a":0,"k":100,"ix":11},"r":{"a":0,"k":0,"ix":10},"p":{"a":0,"k":[189.927,169.5,0],"ix":2},"a":{"a":0,"k":[11.927,14,0],"ix":1},"s":{"a":0,"k":[100,100,100],"ix":6}},"ao":0,"shapes":[{"ty":"gr","it":[{"ind":0,"ty":"sh","ix":1,"ks":{"a":0,"k":{"i":[[0,0],[-87.5,10.5],[-113.5,1]],"o":[[0,0],[78,-15],[113.5,-1]],"v":[[-117.25,118.5],[-20.75,8],[141.25,-94.5]],"c":false},"ix":2},"nm":"Path 1","mn":"ADBE Vector Shape - Group","hd":false},{"ty":"st","c":{"a":0,"k":[0.56862745098,0.784313785329,0.764705942191,1],"ix":3},"o":{"a":0,"k":100,"ix":4},"w":{"a":0,"k":5,"ix":5},"lc":1,"lj":1,"ml":4,"bm":0,"nm":"Stroke 1","mn":"ADBE Vector Graphic - Stroke","hd":false},{"ty":"tr","p":{"a":0,"k":[0,0],"ix":2},"a":{"a":0,"k":[0,0],"ix":1},"s":{"a":0,"k":[100,100],"ix":3},"r":{"a":0,"k":0,"ix":6},"o":{"a":0,"k":100,"ix":7},"sk":{"a":0,"k":0,"ix":4},"sa":{"a":0,"k":0,"ix":5},"nm":"Transform"}],"nm":"Shape 1","np":3,"cix":2,"bm":0,"ix":1,"mn":"ADBE Vector Group","hd":false},{"ty":"tm","s":{"a":0,"k":0,"ix":1},"e":{"a":1,"k":[{"i":{"x":[0.833],"y":[0.833]},"o":{"x":[0.167],"y":[0.167]},"t":10,"s":[0]},{"t":32,"s":[100]}],"ix":2},"o":{"a":0,"k":0,"ix":3},"m":1,"ix":2,"nm":"Trim Paths 1","mn":"ADBE Vector Filter - Trim","hd":false}],"ip":0,"op":60,"st":0,"bm":0},{"ddd":0,"ind":4,"ty":4,"nm":"Line 34","sr":1,"ks":{"o":{"a":0,"k":20,"ix":11},"r":{"a":0,"k":0,"ix":10},"p":{"a":0,"k":[200.5,105,0],"ix":2},"a":{"a":0,"k":[0,0,0],"ix":1},"s":{"a":0,"k":[116.1,-112.57,100],"ix":6}},"ao":0,"shapes":[{"ty":"gr","it":[{"ind":0,"ty":"sh","ix":1,"ks":{"a":0,"k":{"i":[[0,0],[0,0]],"o":[[0,0],[0,0]],"v":[[-128.5,0],[128.5,0]],"c":false},"ix":2},"nm":"Path 1","mn":"ADBE Vector Shape - Group","hd":false},{"ty":"st","c":{"a":0,"k":[0.894117647059,0.894117647059,0.894117647059,1],"ix":3},"o":{"a":0,"k":100,"ix":4},"w":{"a":0,"k":1,"ix":5},"lc":1,"lj":1,"ml":4,"bm":0,"nm":"Stroke 1","mn":"ADBE Vector Graphic - Stroke","hd":false},{"ty":"tr","p":{"a":0,"k":[0,0],"ix":2},"a":{"a":0,"k":[0,0],"ix":1},"s":{"a":0,"k":[100,100],"ix":3},"r":{"a":0,"k":0,"ix":6},"o":{"a":0,"k":100,"ix":7},"sk":{"a":0,"k":0,"ix":4},"sa":{"a":0,"k":0,"ix":5},"nm":"Transform"}],"nm":"Line 29","np":2,"cix":2,"bm":0,"ix":1,"mn":"ADBE Vector Group","hd":false}],"ip":0,"op":60,"st":0,"bm":0},{"ddd":0,"ind":5,"ty":4,"nm":"Line 31","sr":1,"ks":{"o":{"a":0,"k":20,"ix":11},"r":{"a":0,"k":0,"ix":10},"p":{"a":0,"k":[200.5,147.5,0],"ix":2},"a":{"a":0,"k":[0,0,0],"ix":1},"s":{"a":0,"k":[116.1,-112.57,100],"ix":6}},"ao":0,"shapes":[{"ty":"gr","it":[{"ind":0,"ty":"sh","ix":1,"ks":{"a":0,"k":{"i":[[0,0],[0,0]],"o":[[0,0],[0,0]],"v":[[-128.5,0],[128.5,0]],"c":false},"ix":2},"nm":"Path 1","mn":"ADBE Vector Shape - Group","hd":false},{"ty":"st","c":{"a":0,"k":[0.894117647059,0.894117647059,0.894117647059,1],"ix":3},"o":{"a":0,"k":100,"ix":4},"w":{"a":0,"k":1,"ix":5},"lc":1,"lj":1,"ml":4,"bm":0,"nm":"Stroke 1","mn":"ADBE Vector Graphic - Stroke","hd":false},{"ty":"tr","p":{"a":0,"k":[0,0],"ix":2},"a":{"a":0,"k":[0,0],"ix":1},"s":{"a":0,"k":[100,100],"ix":3},"r":{"a":0,"k":0,"ix":6},"o":{"a":0,"k":100,"ix":7},"sk":{"a":0,"k":0,"ix":4},"sa":{"a":0,"k":0,"ix":5},"nm":"Transform"}],"nm":"Line 29","np":2,"cix":2,"bm":0,"ix":1,"mn":"ADBE Vector Group","hd":false}],"ip":0,"op":60,"st":0,"bm":0},{"ddd":0,"ind":6,"ty":4,"nm":"Line 33","sr":1,"ks":{"o":{"a":0,"k":20,"ix":11},"r":{"a":0,"k":0,"ix":10},"p":{"a":0,"k":[200.5,276.5,0],"ix":2},"a":{"a":0,"k":[0,0,0],"ix":1},"s":{"a":0,"k":[116.1,-112.57,100],"ix":6}},"ao":0,"shapes":[{"ty":"gr","it":[{"ind":0,"ty":"sh","ix":1,"ks":{"a":0,"k":{"i":[[0,0],[0,0]],"o":[[0,0],[0,0]],"v":[[-128.5,0],[128.5,0]],"c":false},"ix":2},"nm":"Path 1","mn":"ADBE Vector Shape - Group","hd":false},{"ty":"st","c":{"a":0,"k":[0.894117647059,0.894117647059,0.894117647059,1],"ix":3},"o":{"a":0,"k":100,"ix":4},"w":{"a":0,"k":1,"ix":5},"lc":1,"lj":1,"ml":4,"bm":0,"nm":"Stroke 1","mn":"ADBE Vector Graphic - Stroke","hd":false},{"ty":"tr","p":{"a":0,"k":[0,0],"ix":2},"a":{"a":0,"k":[0,0],"ix":1},"s":{"a":0,"k":[100,100],"ix":3},"r":{"a":0,"k":0,"ix":6},"o":{"a":0,"k":100,"ix":7},"sk":{"a":0,"k":0,"ix":4},"sa":{"a":0,"k":0,"ix":5},"nm":"Transform"}],"nm":"Line 29","np":2,"cix":2,"bm":0,"ix":1,"mn":"ADBE Vector Group","hd":false}],"ip":0,"op":60,"st":0,"bm":0},{"ddd":0,"ind":7,"ty":4,"nm":"Line 32","sr":1,"ks":{"o":{"a":0,"k":20,"ix":11},"r":{"a":0,"k":0,"ix":10},"p":{"a":0,"k":[200.5,233.5,0],"ix":2},"a":{"a":0,"k":[0,0,0],"ix":1},"s":{"a":0,"k":[116.1,-112.57,100],"ix":6}},"ao":0,"shapes":[{"ty":"gr","it":[{"ind":0,"ty":"sh","ix":1,"ks":{"a":0,"k":{"i":[[0,0],[0,0]],"o":[[0,0],[0,0]],"v":[[-128.5,0],[128.5,0]],"c":false},"ix":2},"nm":"Path 1","mn":"ADBE Vector Shape - Group","hd":false},{"ty":"st","c":{"a":0,"k":[0.894117647059,0.894117647059,0.894117647059,1],"ix":3},"o":{"a":0,"k":100,"ix":4},"w":{"a":0,"k":1,"ix":5},"lc":1,"lj":1,"ml":4,"bm":0,"nm":"Stroke 1","mn":"ADBE Vector Graphic - Stroke","hd":false},{"ty":"tr","p":{"a":0,"k":[0,0],"ix":2},"a":{"a":0,"k":[0,0],"ix":1},"s":{"a":0,"k":[100,100],"ix":3},"r":{"a":0,"k":0,"ix":6},"o":{"a":0,"k":100,"ix":7},"sk":{"a":0,"k":0,"ix":4},"sa":{"a":0,"k":0,"ix":5},"nm":"Transform"}],"nm":"Line 29","np":2,"cix":2,"bm":0,"ix":1,"mn":"ADBE Vector Group","hd":false}],"ip":0,"op":60,"st":0,"bm":0},{"ddd":0,"ind":8,"ty":4,"nm":"Line 30","sr":1,"ks":{"o":{"a":0,"k":20,"ix":11},"r":{"a":0,"k":0,"ix":10},"p":{"a":0,"k":[200.5,190,0],"ix":2},"a":{"a":0,"k":[0,0,0],"ix":1},"s":{"a":0,"k":[116.1,-112.57,100],"ix":6}},"ao":0,"shapes":[{"ty":"gr","it":[{"ind":0,"ty":"sh","ix":1,"ks":{"a":0,"k":{"i":[[0,0],[0,0]],"o":[[0,0],[0,0]],"v":[[-128.5,0],[128.5,0]],"c":false},"ix":2},"nm":"Path 1","mn":"ADBE Vector Shape - Group","hd":false},{"ty":"st","c":{"a":0,"k":[0.894117647059,0.894117647059,0.894117647059,1],"ix":3},"o":{"a":0,"k":100,"ix":4},"w":{"a":0,"k":1,"ix":5},"lc":1,"lj":1,"ml":4,"bm":0,"nm":"Stroke 1","mn":"ADBE Vector Graphic - Stroke","hd":false},{"ty":"tr","p":{"a":0,"k":[0,0],"ix":2},"a":{"a":0,"k":[0,0],"ix":1},"s":{"a":0,"k":[100,100],"ix":3},"r":{"a":0,"k":0,"ix":6},"o":{"a":0,"k":100,"ix":7},"sk":{"a":0,"k":0,"ix":4},"sa":{"a":0,"k":0,"ix":5},"nm":"Transform"}],"nm":"Line 29","np":2,"cix":2,"bm":0,"ix":1,"mn":"ADBE Vector Group","hd":false}],"ip":0,"op":60,"st":0,"bm":0},{"ddd":0,"ind":9,"ty":4,"nm":"Line 29","sr":1,"ks":{"o":{"a":0,"k":20,"ix":11},"r":{"a":0,"k":0,"ix":10},"p":{"a":0,"k":[200.5,62,0],"ix":2},"a":{"a":0,"k":[0,0,0],"ix":1},"s":{"a":0,"k":[116.1,-112.57,100],"ix":6}},"ao":0,"shapes":[{"ty":"gr","it":[{"ind":0,"ty":"sh","ix":1,"ks":{"a":0,"k":{"i":[[0,0],[0,0]],"o":[[0,0],[0,0]],"v":[[-128.5,0],[128.5,0]],"c":false},"ix":2},"nm":"Path 1","mn":"ADBE Vector Shape - Group","hd":false},{"ty":"st","c":{"a":0,"k":[0.894117647059,0.894117647059,0.894117647059,1],"ix":3},"o":{"a":0,"k":100,"ix":4},"w":{"a":0,"k":1,"ix":5},"lc":1,"lj":1,"ml":4,"bm":0,"nm":"Stroke 1","mn":"ADBE Vector Graphic - Stroke","hd":false},{"ty":"tr","p":{"a":0,"k":[0,0],"ix":2},"a":{"a":0,"k":[0,0],"ix":1},"s":{"a":0,"k":[100,100],"ix":3},"r":{"a":0,"k":0,"ix":6},"o":{"a":0,"k":100,"ix":7},"sk":{"a":0,"k":0,"ix":4},"sa":{"a":0,"k":0,"ix":5},"nm":"Transform"}],"nm":"Line 29","np":2,"cix":2,"bm":0,"ix":1,"mn":"ADBE Vector Group","hd":false}],"ip":0,"op":60,"st":0,"bm":0},{"ddd":0,"ind":10,"ty":4,"nm":"98% chance","sr":1,"ks":{"o":{"a":0,"k":100,"ix":11},"r":{"a":0,"k":0,"ix":10},"p":{"a":0,"k":[317.499,19.076,0],"ix":2},"a":{"a":0,"k":[0,0,0],"ix":1},"s":{"a":1,"k":[{"i":{"x":[0.667,0.667,0.667],"y":[1,1,1]},"o":{"x":[0.333,0.333,0.333],"y":[0,0,0]},"t":28,"s":[0,0,100]},{"t":36,"s":[100,100,100]}],"ix":6}},"ao":0,"shapes":[{"ty":"gr","it":[{"ind":0,"ty":"sh","ix":1,"ks":{"a":0,"k":{"i":[[0.565,0],[0.16,0.843],[0,0],[-0.299,-0.523],[-0.565,-0.32],[-0.811,0],[-0.587,0.469],[-0.245,0.896],[0,1.387],[0.629,0.981],[1.579,0],[0.608,-0.32],[0.331,-0.587],[0,-0.789],[-0.299,-0.565],[-0.533,-0.288],[-0.683,0],[-0.405,0.181],[-0.235,0.331],[0.235,-0.501]],"o":[[-0.821,0],[0,0],[0.043,0.629],[0.309,0.523],[0.576,0.32],[1.024,0],[0.597,-0.469],[0.256,-0.907],[0,-1.909],[-0.629,-0.981],[-0.821,0],[-0.597,0.32],[-0.32,0.587],[0,0.8],[0.309,0.555],[0.533,0.277],[0.501,0],[0.405,-0.181],[0,1.131],[-0.235,0.501]],"v":[[-11.933,-3.236],[-13.405,-4.5],[-15.933,-4.5],[-15.421,-2.772],[-14.109,-1.508],[-12.029,-1.028],[-9.613,-1.732],[-8.349,-3.78],[-7.965,-7.22],[-8.909,-11.556],[-12.221,-13.028],[-14.365,-12.548],[-15.757,-11.188],[-16.237,-9.124],[-15.789,-7.076],[-14.525,-5.812],[-12.701,-5.396],[-11.341,-5.668],[-10.381,-6.436],[-10.733,-3.988]],"c":true},"ix":2},"nm":"Path 1","mn":"ADBE Vector Shape - Group","hd":false},{"ind":1,"ty":"sh","ix":2,"ks":{"a":0,"k":{"i":[[0.267,-0.277],[0.448,0],[0.277,0.277],[0,0.459],[-0.267,0.277],[-0.469,0],[-0.277,-0.277],[0,-0.512]],"o":[[-0.267,0.267],[-0.512,0],[-0.267,-0.288],[0,-0.491],[0.277,-0.288],[0.469,0],[0.277,0.277],[0,0.469]],"v":[[-11.005,-7.956],[-12.077,-7.556],[-13.261,-7.972],[-13.661,-9.092],[-13.261,-10.244],[-12.141,-10.676],[-11.021,-10.26],[-10.605,-9.076]],"c":true},"ix":2},"nm":"Path 2","mn":"ADBE Vector Shape - Group","hd":false},{"ind":2,"ty":"sh","ix":3,"ks":{"a":0,"k":{"i":[[0,-0.576],[-1.003,-0.533],[0.309,-0.491],[0,-0.661],[-0.384,-0.555],[-0.651,-0.288],[-0.8,0],[-0.651,0.288],[-0.384,0.544],[0,0.757],[0.309,0.48],[0.576,0.277],[-0.267,0.427],[0,0.576],[0.299,0.469],[0.608,0.277],[0.885,0],[0.608,-0.288],[0.299,-0.48]],"o":[[0,1.141],[-0.565,0.267],[-0.309,0.48],[0,0.757],[0.384,0.544],[0.661,0.288],[0.8,0],[0.661,-0.288],[0.384,-0.555],[0,-0.651],[-0.309,-0.491],[0.459,-0.245],[0.277,-0.427],[0,-0.576],[-0.299,-0.48],[-0.597,-0.288],[-0.885,0],[-0.608,0.277],[-0.299,0.469]],"v":[[-6.089,-9.86],[-4.585,-7.348],[-5.897,-6.212],[-6.361,-4.5],[-5.785,-2.532],[-4.233,-1.284],[-2.041,-0.852],[0.135,-1.284],[1.703,-2.532],[2.279,-4.5],[1.815,-6.196],[0.487,-7.348],[1.575,-8.356],[1.991,-9.86],[1.543,-11.428],[0.183,-12.564],[-2.041,-12.996],[-4.281,-12.564],[-5.641,-11.428]],"c":true},"ix":2},"nm":"Path 3","mn":"ADBE Vector Shape - Group","hd":false},{"ind":3,"ty":"sh","ix":4,"ks":{"a":0,"k":{"i":[[-0.245,-0.245],[0,-0.437],[0.256,-0.245],[0.405,0],[0.256,0.235],[0,0.416],[-0.245,0.245],[-0.416,0]],"o":[[0.256,0.235],[0,0.416],[-0.256,0.245],[-0.405,0],[-0.256,-0.245],[0,-0.437],[0.256,-0.245],[0.416,0]],"v":[[-1.049,-10.452],[-0.665,-9.444],[-1.049,-8.452],[-2.041,-8.084],[-3.033,-8.436],[-3.417,-9.428],[-3.049,-10.452],[-2.041,-10.82]],"c":true},"ix":2},"nm":"Path 4","mn":"ADBE Vector Shape - Group","hd":false},{"ind":4,"ty":"sh","ix":5,"ks":{"a":0,"k":{"i":[[-0.309,0.267],[-0.501,0],[-0.299,-0.277],[0,-0.469],[0.299,-0.288],[0.512,0],[0.309,0.288],[0,0.448]],"o":[[0.309,-0.277],[0.491,0],[0.309,0.277],[0,0.448],[-0.288,0.288],[-0.512,0],[-0.299,-0.288],[0,-0.48]],"v":[[-3.257,-5.748],[-2.041,-6.164],[-0.857,-5.748],[-0.393,-4.628],[-0.841,-3.524],[-2.041,-3.092],[-3.273,-3.524],[-3.721,-4.628]],"c":true},"ix":2},"nm":"Path 5","mn":"ADBE Vector Shape - Group","hd":false},{"ind":5,"ty":"sh","ix":6,"ks":{"a":0,"k":{"i":[[0.501,-0.469],[0,-0.864],[-0.491,-0.469],[-0.789,0],[-0.491,0.469],[0,0.864],[0.491,0.469],[0.789,0]],"o":[[-0.491,0.469],[0,0.864],[0.501,0.469],[0.789,0],[0.491,-0.469],[0,-0.864],[-0.491,-0.469],[-0.789,0]],"v":[[4.382,-11.812],[3.646,-9.812],[4.382,-7.812],[6.318,-7.108],[8.238,-7.812],[8.974,-9.812],[8.238,-11.812],[6.318,-12.516]],"c":true},"ix":2},"nm":"Path 6","mn":"ADBE Vector Shape - Group","hd":false},{"ind":6,"ty":"sh","ix":7,"ks":{"a":0,"k":{"i":[[0,0],[0,0],[0,0],[0,0]],"o":[[0,0],[0,0],[0,0],[0,0]],"v":[[8.35,-1.076],[14.51,-12.34],[11.87,-12.34],[5.71,-1.076]],"c":true},"ix":2},"nm":"Path 7","mn":"ADBE Vector Shape - Group","hd":false},{"ind":7,"ty":"sh","ix":8,"ks":{"a":0,"k":{"i":[[0,0.725],[-0.512,0],[0,-0.736],[0.139,-0.181],[0.245,0]],"o":[[0,-0.736],[0.523,0],[0,0.363],[-0.139,0.181],[-0.512,0]],"v":[[5.534,-9.812],[6.302,-10.916],[7.086,-9.812],[6.878,-8.996],[6.302,-8.724]],"c":true},"ix":2},"nm":"Path 8","mn":"ADBE Vector Shape - Group","hd":false},{"ind":8,"ty":"sh","ix":9,"ks":{"a":0,"k":{"i":[[0.491,-0.469],[0,-0.864],[-0.491,-0.469],[-0.789,0],[-0.491,0.469],[0,0.864],[0.491,0.469],[0.789,0]],"o":[[-0.491,0.469],[0,0.864],[0.491,0.469],[0.789,0],[0.491,-0.469],[0,-0.864],[-0.491,-0.469],[-0.789,0]],"v":[[11.998,-5.604],[11.262,-3.604],[11.998,-1.604],[13.918,-0.9],[15.838,-1.604],[16.574,-3.604],[15.838,-5.604],[13.918,-6.308]],"c":true},"ix":2},"nm":"Path 9","mn":"ADBE Vector Shape - Group","hd":false},{"ind":9,"ty":"sh","ix":10,"ks":{"a":0,"k":{"i":[[-0.128,0.181],[-0.245,0],[-0.139,-0.192],[0,-0.363],[0.139,-0.181],[0.245,0],[0,0.725]],"o":[[0.139,-0.181],[0.245,0],[0.139,0.181],[0,0.363],[-0.139,0.181],[-0.512,0],[0,-0.373]],"v":[[13.326,-4.436],[13.902,-4.708],[14.478,-4.42],[14.686,-3.604],[14.478,-2.788],[13.902,-2.516],[13.134,-3.604]],"c":true},"ix":2},"nm":"Path 10","mn":"ADBE Vector Shape - Group","hd":false},{"ind":10,"ty":"sh","ix":11,"ks":{"a":0,"k":{"i":[[0.312,-0.563],[0,-0.754],[-0.303,-0.563],[-0.546,-0.303],[-0.711,0],[-0.615,0.485],[-0.191,0.849],[0,0],[0.572,0],[0.243,0.312],[0,0.589],[-0.243,0.312],[-0.407,0],[-0.199,-0.555],[0,0],[0.615,0.477],[0.91,0],[0.555,-0.303]],"o":[[-0.303,0.563],[0,0.754],[0.312,0.563],[0.555,0.303],[0.901,0],[0.615,-0.485],[0,0],[-0.199,0.555],[-0.407,0],[-0.243,-0.321],[0,-0.589],[0.243,-0.321],[0.572,0],[0,0],[-0.191,-0.867],[-0.607,-0.477],[-0.711,0],[-0.546,0.303]],"v":[[-24.227,7.321],[-24.682,9.297],[-24.227,11.273],[-22.94,12.573],[-21.042,13.028],[-18.767,12.3],[-17.558,10.298],[-19.924,10.298],[-21.081,11.13],[-22.056,10.662],[-22.42,9.297],[-22.056,7.945],[-21.081,7.464],[-19.924,8.296],[-17.558,8.296],[-18.767,6.281],[-21.042,5.566],[-22.94,6.021]],"c":true},"ix":2},"nm":"Path 11","mn":"ADBE Vector Shape - Group","hd":false},{"ind":11,"ty":"sh","ix":12,"ks":{"a":0,"k":{"i":[[0.503,0.546],[0.832,0],[0.39,-0.191],[0.225,-0.321],[0,0],[0,0],[0,0],[0,0],[0,0],[-0.251,0.269],[-0.425,0],[-0.251,-0.269],[0,-0.485],[0,0],[0,0],[0,0]],"o":[[-0.503,-0.555],[-0.485,0],[-0.39,0.191],[0,0],[0,0],[0,0],[0,0],[0,0],[0,-0.485],[0.251,-0.269],[0.425,0],[0.251,0.269],[0,0],[0,0],[0,0],[0,-0.962]],"v":[[-9.908,6.424],[-11.91,5.592],[-13.223,5.878],[-14.146,6.645],[-14.146,3.304],[-16.369,3.304],[-16.369,12.924],[-14.146,12.924],[-14.146,8.985],[-13.769,7.854],[-12.755,7.451],[-11.741,7.854],[-11.364,8.985],[-11.364,12.924],[-9.154,12.924],[-9.154,8.686]],"c":true},"ix":2},"nm":"Path 12","mn":"ADBE Vector Shape - Group","hd":false},{"ind":12,"ty":"sh","ix":13,"ks":{"a":0,"k":{"i":[[0.286,-0.563],[0,-0.745],[-0.277,-0.572],[-0.485,-0.312],[-0.589,0],[-0.381,0.208],[-0.217,0.338],[0,0],[0,0],[0,0],[0,0],[0,0],[0.39,0.208],[0.511,0],[0.485,-0.303]],"o":[[-0.277,0.563],[0,0.745],[0.286,0.563],[0.485,0.303],[0.511,0],[0.39,-0.208],[0,0],[0,0],[0,0],[0,0],[0,0],[-0.208,-0.338],[-0.381,-0.208],[-0.598,0],[-0.485,0.303]],"v":[[-7.636,7.321],[-8.052,9.284],[-7.636,11.26],[-6.479,12.573],[-4.867,13.028],[-3.528,12.716],[-2.618,11.897],[-2.618,12.924],[-0.395,12.924],[-0.395,5.67],[-2.618,5.67],[-2.618,6.697],[-3.515,5.878],[-4.854,5.566],[-6.479,6.021]],"c":true},"ix":2},"nm":"Path 13","mn":"ADBE Vector Shape - Group","hd":false},{"ind":13,"ty":"sh","ix":14,"ks":{"a":0,"k":{"i":[[-0.303,-0.321],[0,-0.555],[0.312,-0.321],[0.442,0],[0.312,0.321],[0,0.555],[-0.303,0.312],[-0.442,0]],"o":[[0.312,0.321],[0,0.555],[-0.303,0.321],[-0.442,0],[-0.303,-0.329],[0,-0.555],[0.312,-0.321],[0.442,0]],"v":[[-3.086,7.984],[-2.618,9.297],[-3.086,10.61],[-4.204,11.091],[-5.335,10.61],[-5.79,9.284],[-5.335,7.984],[-4.204,7.503]],"c":true},"ix":2},"nm":"Path 14","mn":"ADBE Vector Shape - Group","hd":false},{"ind":14,"ty":"sh","ix":15,"ks":{"a":0,"k":{"i":[[0.511,0.546],[0.849,0],[0.381,-0.191],[0.225,-0.321],[0,0],[0,0],[0,0],[0,0],[0,0],[-0.251,0.269],[-0.425,0],[-0.251,-0.269],[0,-0.485],[0,0],[0,0],[0,0]],"o":[[-0.503,-0.555],[-0.477,0],[-0.381,0.182],[0,0],[0,0],[0,0],[0,0],[0,0],[0,-0.485],[0.251,-0.269],[0.425,0],[0.251,0.269],[0,0],[0,0],[0,0],[0,-0.962]],"v":[[7.662,6.424],[5.634,5.592],[4.347,5.878],[3.437,6.632],[3.437,5.67],[1.214,5.67],[1.214,12.924],[3.437,12.924],[3.437,8.985],[3.814,7.854],[4.828,7.451],[5.842,7.854],[6.219,8.985],[6.219,12.924],[8.429,12.924],[8.429,8.686]],"c":true},"ix":2},"nm":"Path 15","mn":"ADBE Vector Shape - Group","hd":false},{"ind":15,"ty":"sh","ix":16,"ks":{"a":0,"k":{"i":[[0.312,-0.563],[0,-0.754],[-0.303,-0.563],[-0.546,-0.303],[-0.711,0],[-0.615,0.485],[-0.191,0.849],[0,0],[0.572,0],[0.243,0.312],[0,0.589],[-0.243,0.312],[-0.407,0],[-0.199,-0.555],[0,0],[0.615,0.477],[0.91,0],[0.555,-0.303]],"o":[[-0.303,0.563],[0,0.754],[0.312,0.563],[0.555,0.303],[0.901,0],[0.615,-0.485],[0,0],[-0.199,0.555],[-0.407,0],[-0.243,-0.321],[0,-0.589],[0.243,-0.321],[0.572,0],[0,0],[-0.191,-0.867],[-0.607,-0.477],[-0.711,0],[-0.546,0.303]],"v":[[9.986,7.321],[9.531,9.297],[9.986,11.273],[11.273,12.573],[13.171,13.028],[15.446,12.3],[16.655,10.298],[14.289,10.298],[13.132,11.13],[12.157,10.662],[11.793,9.297],[12.157,7.945],[13.132,7.464],[14.289,8.296],[16.655,8.296],[15.446,6.281],[13.171,5.566],[11.273,6.021]],"c":true},"ix":2},"nm":"Path 16","mn":"ADBE Vector Shape - Group","hd":false},{"ind":16,"ty":"sh","ix":17,"ks":{"a":0,"k":{"i":[[0,0],[0,0.208],[0.312,0.546],[0.546,0.295],[0.702,0],[0.555,-0.303],[0.312,-0.563],[0,-0.754],[-0.312,-0.563],[-0.555,-0.303],[-0.711,0],[-0.477,0.217],[-0.312,0.381],[-0.121,0.477],[0,0],[0.555,0],[0.26,0.234],[0.035,0.451]],"o":[[0.026,-0.225],[0,-0.728],[-0.303,-0.546],[-0.546,-0.295],[-0.719,0],[-0.555,0.303],[-0.303,0.563],[0,0.754],[0.312,0.563],[0.555,0.303],[0.589,0],[0.477,-0.217],[0.321,-0.381],[0,0],[-0.217,0.468],[-0.373,0],[-0.251,-0.243],[0,0]],"v":[[24.643,9.83],[24.682,9.18],[24.214,7.269],[22.94,6.008],[21.068,5.566],[19.157,6.021],[17.857,7.321],[17.402,9.297],[17.87,11.273],[19.17,12.573],[21.068,13.028],[22.667,12.703],[23.85,11.806],[24.513,10.519],[22.147,10.519],[20.99,11.221],[20.041,10.87],[19.612,9.83]],"c":true},"ix":2},"nm":"Path 17","mn":"ADBE Vector Shape - Group","hd":false},{"ind":17,"ty":"sh","ix":18,"ks":{"a":0,"k":{"i":[[-0.26,-0.225],[0,-0.381],[0,0],[-0.251,0.217],[-0.373,0]],"o":[[0.26,0.225],[0,0],[0.061,-0.399],[0.26,-0.217],[0.39,0]],"v":[[22.017,7.685],[22.407,8.595],[19.625,8.595],[20.093,7.672],[21.042,7.347]],"c":true},"ix":2},"nm":"Path 18","mn":"ADBE Vector Shape - Group","hd":false},{"ty":"mm","mm":1,"nm":"Merge Paths 1","mn":"ADBE Vector Filter - Merge","hd":false},{"ty":"fl","c":{"a":0,"k":[1,1,1,1],"ix":4},"o":{"a":0,"k":100,"ix":5},"r":1,"bm":0,"nm":"Fill 1","mn":"ADBE Vector Graphic - Fill","hd":false},{"ty":"tr","p":{"a":0,"k":[0,0],"ix":2},"a":{"a":0,"k":[0,0],"ix":1},"s":{"a":0,"k":[100,100],"ix":3},"r":{"a":0,"k":0,"ix":6},"o":{"a":0,"k":100,"ix":7},"sk":{"a":0,"k":0,"ix":4},"sa":{"a":0,"k":0,"ix":5},"nm":"Transform"}],"nm":"98% chance","np":20,"cix":2,"bm":0,"ix":1,"mn":"ADBE Vector Group","hd":false}],"ip":0,"op":60,"st":0,"bm":0},{"ddd":0,"ind":11,"ty":4,"nm":"Shape","sr":1,"ks":{"o":{"a":0,"k":100,"ix":11},"r":{"a":0,"k":0,"ix":10},"p":{"a":0,"k":[316.75,24.224,0],"ix":2},"a":{"a":0,"k":[0,0,0],"ix":1},"s":{"a":1,"k":[{"i":{"x":[0.667,0.667,0.667],"y":[1,1,1]},"o":{"x":[0.333,0.333,0.333],"y":[0,0,0]},"t":28,"s":[0,0,100]},{"t":36,"s":[100,100,100]}],"ix":6}},"ao":0,"shapes":[{"ty":"gr","it":[{"ind":0,"ty":"sh","ix":1,"ks":{"a":0,"k":{"i":[[0,0],[-1.382,1.93],[-0.045,0.055],[-2.931,0.042],[-0.149,0],[0,0],[-1.141,0.619],[-0.61,1.157],[0,3.164],[0,0],[0.61,1.157],[1.141,0.619],[3.12,0],[0,0],[1.141,-0.619],[0.61,-1.157],[0,-3.164],[0,0],[-0.61,-1.157],[-1.141,-0.619],[-3.12,0],[0,0],[-0.65,-0.179],[-0.484,-0.35],[-0.882,-1.098]],"o":[[1.321,1.93],[0.093,-0.116],[1.868,-2.259],[0.071,-0.001],[0,0],[3.12,0],[1.141,-0.619],[0.61,-1.157],[0,0],[0,-3.164],[-0.61,-1.157],[-1.141,-0.619],[0,0],[-3.12,0],[-1.141,0.619],[-0.61,1.157],[0,0],[0,3.164],[0.61,1.157],[1.141,0.619],[0,0],[1.409,0],[0.576,0.158],[0.547,0.395],[0,0]],"v":[[-2.904,22.027],[2.437,22.027],[2.622,21.798],[10.187,18.171],[10.481,18.17],[29.526,18.17],[34.919,17.222],[37.565,14.539],[38.5,9.07],[38.5,-14.374],[37.565,-19.843],[34.919,-22.526],[29.526,-23.474],[-29.526,-23.474],[-34.919,-22.526],[-37.565,-19.843],[-38.5,-14.374],[-38.5,9.07],[-37.565,14.539],[-34.919,17.222],[-29.526,18.17],[-9.836,18.17],[-7.073,18.349],[-5.469,19.118],[-3.599,21.16]],"c":true},"ix":2},"nm":"Path 1","mn":"ADBE Vector Shape - Group","hd":false},{"ty":"fl","c":{"a":0,"k":[0.952941179276,0.57647061348,0.341176480055,1],"ix":4},"o":{"a":0,"k":100,"ix":5},"r":1,"bm":0,"nm":"Fill 1","mn":"ADBE Vector Graphic - Fill","hd":false},{"ty":"tr","p":{"a":0,"k":[0,0],"ix":2},"a":{"a":0,"k":[0,0],"ix":1},"s":{"a":0,"k":[100,100],"ix":3},"r":{"a":0,"k":0,"ix":6},"o":{"a":0,"k":100,"ix":7},"sk":{"a":0,"k":0,"ix":4},"sa":{"a":0,"k":0,"ix":5},"nm":"Transform"}],"nm":"Shape","np":2,"cix":2,"bm":0,"ix":1,"mn":"ADBE Vector Group","hd":false}],"ip":0,"op":60,"st":0,"bm":0},{"ddd":0,"ind":12,"ty":4,"nm":"Vector","sr":1,"ks":{"o":{"a":0,"k":100,"ix":11},"r":{"a":0,"k":0,"ix":10},"p":{"a":0,"k":[20.1,168.44,0],"ix":2},"a":{"a":0,"k":[0,0,0],"ix":1},"s":{"a":0,"k":[100,100,100],"ix":6}},"ao":0,"shapes":[{"ty":"gr","it":[{"ind":0,"ty":"sh","ix":1,"ks":{"a":0,"k":{"i":[[0.479,-0.824],[0.008,-1.457],[-0.47,-0.819],[-1.186,0.007],[-0.479,0.824],[-0.008,1.482],[0.47,0.81],[1.177,-0.006]],"o":[[-0.479,0.816],[-0.008,1.482],[0.47,0.819],[1.177,-0.006],[0.479,-0.824],[0.008,-1.457],[-0.47,-0.819],[-1.186,0.007]],"v":[[8.348,102.872],[7.618,106.281],[8.311,109.732],[10.794,110.951],[13.278,109.705],[14.008,106.246],[13.315,102.845],[10.844,101.626]],"c":true},"ix":2},"nm":"Path 1","mn":"ADBE Vector Shape - Group","hd":false},{"ind":1,"ty":"sh","ix":2,"ks":{"a":0,"k":{"i":[[-0.09,-0.516],[0.004,-0.737],[0.104,-0.517],[0.307,-0.315],[0.567,-0.003],[0.303,0.312],[0.099,0.516],[-0.004,0.762],[-0.096,0.509],[-0.298,0.315],[-0.576,0.003],[-0.295,-0.312]],"o":[[0.099,0.508],[-0.004,0.762],[-0.096,0.517],[-0.298,0.315],[-0.576,0.003],[-0.295,-0.312],[-0.09,-0.516],[0.004,-0.737],[0.104,-0.517],[0.307,-0.315],[0.567,-0.003],[0.303,0.312]],"v":[[12.722,104.385],[12.865,106.252],[12.702,108.171],[12.098,109.419],[10.8,109.897],[9.481,109.434],[8.891,108.192],[8.761,106.275],[8.911,104.406],[9.515,103.158],[10.839,102.681],[12.132,103.144]],"c":true},"ix":2},"nm":"Path 2","mn":"ADBE Vector Shape - Group","hd":false},{"ind":2,"ty":"sh","ix":3,"ks":{"a":0,"k":{"i":[[0.613,-0.562],[1.08,-0.87],[0,0],[0,0],[0,0],[0,0],[-0.536,0.503],[-0.419,0.663],[-0.004,0.703],[0.514,0.48],[0.872,-0.005],[0.545,-0.52],[0.039,-0.949],[0,0],[-0.315,0.357],[-0.576,0.003],[-0.261,-0.32],[0.003,-0.55],[0.427,-0.612]],"o":[[-0.613,0.554],[0,0],[0,0],[0,0],[0,0],[0.834,-0.674],[0.536,-0.511],[0.427,-0.671],[0.005,-0.847],[-0.506,-0.48],[-0.855,0.005],[-0.545,0.52],[0,0],[0.029,-0.601],[0.324,-0.366],[0.593,-0.003],[0.269,0.312],[-0.003,0.584],[-0.418,0.604]],"v":[[-6.896,65.242],[-9.436,67.377],[-9.44,68.203],[-3.33,68.169],[-3.324,67.204],[-7.694,67.228],[-5.64,65.464],[-4.207,63.703],[-3.561,61.641],[-4.325,59.651],[-6.392,58.938],[-8.492,59.725],[-9.368,61.927],[-8.25,61.921],[-7.734,60.483],[-6.385,59.929],[-5.104,60.405],[-4.705,61.698],[-5.35,63.493]],"c":true},"ix":2},"nm":"Path 3","mn":"ADBE Vector Shape - Group","hd":false},{"ind":3,"ty":"sh","ix":4,"ks":{"a":0,"k":{"i":[[0.479,-0.824],[0.008,-1.457],[-0.47,-0.819],[-1.186,0.007],[-0.479,0.824],[-0.008,1.482],[0.47,0.81],[1.177,-0.006]],"o":[[-0.479,0.816],[-0.008,1.482],[0.47,0.819],[1.177,-0.006],[0.479,-0.824],[0.008,-1.457],[-0.47,-0.819],[-1.186,0.007]],"v":[[-1.239,60.167],[-1.968,63.576],[-1.276,67.028],[1.208,68.246],[3.691,67],[4.422,63.541],[3.729,60.14],[1.258,58.922]],"c":true},"ix":2},"nm":"Path 4","mn":"ADBE Vector Shape - Group","hd":false},{"ind":4,"ty":"sh","ix":5,"ks":{"a":0,"k":{"i":[[-0.09,-0.516],[0.004,-0.737],[0.104,-0.517],[0.307,-0.315],[0.567,-0.003],[0.303,0.312],[0.099,0.516],[-0.004,0.762],[-0.096,0.509],[-0.298,0.315],[-0.576,0.003],[-0.295,-0.312]],"o":[[0.099,0.508],[-0.004,0.762],[-0.096,0.517],[-0.298,0.315],[-0.576,0.003],[-0.295,-0.312],[-0.09,-0.516],[0.004,-0.737],[0.104,-0.517],[0.307,-0.315],[0.567,-0.003],[0.303,0.312]],"v":[[3.136,61.681],[3.278,63.547],[3.115,65.466],[2.512,66.715],[1.213,67.192],[-0.105,66.729],[-0.696,65.487],[-0.825,63.57],[-0.675,61.702],[-0.072,60.453],[1.252,59.976],[2.545,60.439]],"c":true},"ix":2},"nm":"Path 5","mn":"ADBE Vector Shape - Group","hd":false},{"ind":5,"ty":"sh","ix":6,"ks":{"a":0,"k":{"i":[[0.349,-0.349],[0.003,-0.576],[-0.345,-0.345],[-0.542,0.003],[-0.349,0.341],[-0.003,0.584],[0.345,0.337],[0.542,-0.003]],"o":[[-0.349,0.341],[-0.003,0.584],[0.345,0.337],[0.542,-0.003],[0.349,-0.349],[0.003,-0.576],[-0.345,-0.345],[-0.542,0.003]],"v":[[6.296,59.732],[5.768,61.107],[6.281,62.502],[7.612,63.003],[8.949,62.487],[9.477,61.087],[8.964,59.718],[7.633,59.204]],"c":true},"ix":2},"nm":"Path 6","mn":"ADBE Vector Shape - Group","hd":false},{"ind":6,"ty":"sh","ix":7,"ks":{"a":0,"k":{"i":[[0,0],[0,0],[0,0],[0,0]],"o":[[0,0],[0,0],[0,0],[0,0]],"v":[[8.003,68.209],[13.196,59.313],[12.053,59.32],[6.86,68.215]],"c":true},"ix":2},"nm":"Path 7","mn":"ADBE Vector Shape - Group","hd":false},{"ind":7,"ty":"sh","ix":8,"ks":{"a":0,"k":{"i":[[-0.162,0.196],[-0.288,0.002],[-0.168,-0.202],[0.002,-0.39],[0.171,-0.213],[0.288,-0.002],[0.168,0.202],[-0.002,0.39]],"o":[[0.17,-0.204],[0.288,-0.002],[0.168,0.194],[-0.002,0.381],[-0.17,0.204],[-0.288,0.002],[-0.16,-0.202],[0.002,-0.39]],"v":[[6.941,60.224],[7.629,59.916],[8.313,60.217],[8.562,61.092],[8.304,61.983],[7.616,62.291],[6.932,61.99],[6.695,61.102]],"c":true},"ix":2},"nm":"Path 8","mn":"ADBE Vector Shape - Group","hd":false},{"ind":8,"ty":"sh","ix":9,"ks":{"a":0,"k":{"i":[[0.349,-0.349],[0.003,-0.584],[-0.345,-0.345],[-0.542,0.003],[-0.341,0.349],[-0.003,0.576],[0.345,0.337],[0.542,-0.003]],"o":[[-0.349,0.341],[-0.003,0.584],[0.345,0.337],[0.542,-0.003],[0.349,-0.349],[0.003,-0.584],[-0.337,-0.345],[-0.542,0.003]],"v":[[11.133,65.054],[10.604,66.441],[11.118,67.836],[12.449,68.337],[13.773,67.809],[14.301,66.421],[13.788,65.039],[12.469,64.526]],"c":true},"ix":2},"nm":"Path 9","mn":"ADBE Vector Shape - Group","hd":false},{"ind":9,"ty":"sh","ix":10,"ks":{"a":0,"k":{"i":[[-0.17,0.196],[-0.288,0.002],[-0.168,-0.202],[0.002,-0.39],[0.17,-0.204],[0.288,-0.002],[0.168,0.194],[-0.002,0.381]],"o":[[0.17,-0.204],[0.288,-0.002],[0.168,0.194],[-0.002,0.381],[-0.17,0.196],[-0.288,0.002],[-0.168,-0.202],[0.002,-0.39]],"v":[[11.765,65.559],[12.453,65.25],[13.137,65.551],[13.386,66.426],[13.128,67.304],[12.44,67.6],[11.756,67.312],[11.506,66.437]],"c":true},"ix":2},"nm":"Path 10","mn":"ADBE Vector Shape - Group","hd":false},{"ind":10,"ty":"sh","ix":11,"ks":{"a":0,"k":{"i":[[0,0],[0,0],[0,0],[0,0],[0,0],[0,0],[0,0],[0,0],[0,0],[0,0],[0,0]],"o":[[0,0],[0,0],[0,0],[0,0],[0,0],[0,0],[0,0],[0,0],[0,0],[0,0],[0,0]],"v":[[-10.247,22.631],[-10.252,23.507],[-5.551,23.481],[-5.562,25.527],[-4.419,25.521],[-4.408,23.475],[-3.138,23.468],[-3.132,22.465],[-4.403,22.472],[-4.37,16.425],[-5.755,16.432]],"c":true},"ix":2},"nm":"Path 11","mn":"ADBE Vector Shape - Group","hd":false},{"ind":11,"ty":"sh","ix":12,"ks":{"a":0,"k":{"i":[[0,0],[0,0],[0,0]],"o":[[0,0],[0,0],[0,0]],"v":[[-8.912,22.496],[-5.469,17.637],[-5.495,22.478]],"c":true},"ix":2},"nm":"Path 12","mn":"ADBE Vector Shape - Group","hd":false},{"ind":12,"ty":"sh","ix":13,"ks":{"a":0,"k":{"i":[[0.479,-0.824],[0.008,-1.457],[-0.47,-0.819],[-1.186,0.007],[-0.479,0.824],[-0.008,1.482],[0.47,0.81],[1.177,-0.006]],"o":[[-0.479,0.816],[-0.008,1.482],[0.47,0.819],[1.177,-0.006],[0.479,-0.824],[0.008,-1.457],[-0.47,-0.819],[-1.186,0.007]],"v":[[-1.239,17.411],[-1.968,20.82],[-1.276,24.271],[1.208,25.49],[3.691,24.244],[4.422,20.784],[3.728,17.384],[1.258,16.165]],"c":true},"ix":2},"nm":"Path 13","mn":"ADBE Vector Shape - Group","hd":false},{"ind":13,"ty":"sh","ix":14,"ks":{"a":0,"k":{"i":[[-0.09,-0.516],[0.004,-0.737],[0.104,-0.517],[0.307,-0.315],[0.567,-0.003],[0.303,0.312],[0.099,0.516],[-0.004,0.762],[-0.096,0.509],[-0.298,0.315],[-0.576,0.003],[-0.295,-0.312]],"o":[[0.099,0.508],[-0.004,0.762],[-0.096,0.517],[-0.298,0.315],[-0.576,0.003],[-0.295,-0.312],[-0.09,-0.516],[0.004,-0.737],[0.104,-0.517],[0.307,-0.315],[0.567,-0.003],[0.303,0.312]],"v":[[3.136,18.924],[3.278,20.791],[3.115,22.71],[2.512,23.958],[1.213,24.435],[-0.105,23.972],[-0.696,22.731],[-0.825,20.813],[-0.675,18.945],[-0.072,17.697],[1.252,17.219],[2.545,17.682]],"c":true},"ix":2},"nm":"Path 14","mn":"ADBE Vector Shape - Group","hd":false},{"ind":14,"ty":"sh","ix":15,"ks":{"a":0,"k":{"i":[[0.349,-0.349],[0.003,-0.576],[-0.345,-0.345],[-0.542,0.003],[-0.349,0.341],[-0.003,0.584],[0.345,0.337],[0.542,-0.003]],"o":[[-0.349,0.341],[-0.003,0.584],[0.345,0.337],[0.542,-0.003],[0.349,-0.349],[0.003,-0.576],[-0.345,-0.345],[-0.542,0.003]],"v":[[6.296,16.976],[5.768,18.351],[6.281,19.745],[7.612,20.246],[8.949,19.731],[9.477,18.33],[8.964,16.961],[7.633,16.448]],"c":true},"ix":2},"nm":"Path 15","mn":"ADBE Vector Shape - Group","hd":false},{"ind":15,"ty":"sh","ix":16,"ks":{"a":0,"k":{"i":[[0,0],[0,0],[0,0],[0,0]],"o":[[0,0],[0,0],[0,0],[0,0]],"v":[[8.003,25.452],[13.196,16.557],[12.053,16.563],[6.86,25.459]],"c":true},"ix":2},"nm":"Path 16","mn":"ADBE Vector Shape - Group","hd":false},{"ind":16,"ty":"sh","ix":17,"ks":{"a":0,"k":{"i":[[-0.162,0.196],[-0.288,0.002],[-0.168,-0.202],[0.002,-0.39],[0.171,-0.213],[0.288,-0.002],[0.168,0.202],[-0.002,0.39]],"o":[[0.17,-0.204],[0.288,-0.002],[0.168,0.194],[-0.002,0.381],[-0.17,0.204],[-0.288,0.002],[-0.16,-0.202],[0.002,-0.39]],"v":[[6.941,17.468],[7.629,17.159],[8.313,17.46],[8.562,18.335],[8.304,19.226],[7.616,19.535],[6.932,19.234],[6.695,18.346]],"c":true},"ix":2},"nm":"Path 17","mn":"ADBE Vector Shape - Group","hd":false},{"ind":17,"ty":"sh","ix":18,"ks":{"a":0,"k":{"i":[[0.349,-0.349],[0.003,-0.584],[-0.345,-0.345],[-0.542,0.003],[-0.341,0.349],[-0.003,0.576],[0.345,0.337],[0.542,-0.003]],"o":[[-0.349,0.341],[-0.003,0.584],[0.345,0.337],[0.542,-0.003],[0.349,-0.349],[0.003,-0.584],[-0.337,-0.345],[-0.542,0.003]],"v":[[11.133,22.297],[10.604,23.685],[11.118,25.08],[12.449,25.58],[13.773,25.052],[14.301,23.665],[13.788,22.283],[12.469,21.769]],"c":true},"ix":2},"nm":"Path 18","mn":"ADBE Vector Shape - Group","hd":false},{"ind":18,"ty":"sh","ix":19,"ks":{"a":0,"k":{"i":[[-0.17,0.196],[-0.288,0.002],[-0.168,-0.202],[0.002,-0.39],[0.17,-0.204],[0.288,-0.002],[0.168,0.194],[-0.002,0.381]],"o":[[0.17,-0.204],[0.288,-0.002],[0.168,0.194],[-0.002,0.381],[-0.17,0.196],[-0.288,0.002],[-0.168,-0.202],[0.002,-0.39]],"v":[[11.765,22.802],[12.453,22.493],[13.137,22.795],[13.386,23.67],[13.128,24.548],[12.44,24.844],[11.756,24.555],[11.506,23.68]],"c":true},"ix":2},"nm":"Path 19","mn":"ADBE Vector Shape - Group","hd":false},{"ind":19,"ty":"sh","ix":20,"ks":{"a":0,"k":{"i":[[-0.754,0.004],[-0.181,-0.939],[0,0],[0.472,0.446],[0.83,-0.005],[0.017,-3.108],[-0.191,-0.685],[-0.489,-0.387],[-0.872,0.005],[-0.45,0.273],[-0.223,0.459],[-0.003,0.576],[0.522,0.539],[0.872,-0.005],[0.459,-0.257],[0.197,-0.441],[-0.376,0.578]],"o":[[0.974,-0.005],[0,0],[-0.081,-0.686],[-0.472,-0.446],[-2.168,0.012],[-0.005,1.008],[0.191,0.685],[0.489,0.387],[0.644,-0.004],[0.459,-0.274],[0.231,-0.459],[0.005,-0.957],[-0.514,-0.539],[-0.559,0.003],[-0.45,0.248],[-0.001,-1.33],[0.376,-0.586]],"v":[[-6.633,-25.635],[-4.9,-24.234],[-3.833,-24.24],[-4.662,-25.938],[-6.615,-26.601],[-9.892,-21.92],[-9.614,-19.381],[-8.594,-17.774],[-6.552,-17.2],[-4.911,-17.616],[-3.888,-18.714],[-3.537,-20.266],[-4.313,-22.51],[-6.392,-23.312],[-7.918,-22.922],[-8.889,-21.888],[-8.327,-24.749]],"c":true},"ix":2},"nm":"Path 20","mn":"ADBE Vector Shape - Group","hd":false},{"ind":20,"ty":"sh","ix":21,"ks":{"a":0,"k":{"i":[[-0.323,0.146],[-0.364,0.002],[-0.337,-0.379],[0.004,-0.661],[0.358,-0.375],[0.593,-0.003],[0.37,0.396],[-0.003,0.644],[-0.196,0.297]],"o":[[0.323,-0.154],[0.652,-0.004],[0.337,0.371],[-0.003,0.627],[-0.349,0.366],[-0.694,0.004],[-0.37,-0.404],[0.002,-0.432],[0.205,-0.306]],"v":[[-7.668,-22.098],[-6.638,-22.332],[-5.155,-21.769],[-4.655,-20.222],[-5.197,-18.72],[-6.61,-18.166],[-8.207,-18.754],[-8.758,-20.326],[-8.46,-21.42]],"c":true},"ix":2},"nm":"Path 21","mn":"ADBE Vector Shape - Group","hd":false},{"ind":21,"ty":"sh","ix":22,"ks":{"a":0,"k":{"i":[[0.479,-0.824],[0.008,-1.457],[-0.47,-0.819],[-1.186,0.007],[-0.479,0.824],[-0.008,1.482],[0.47,0.81],[1.177,-0.006]],"o":[[-0.479,0.816],[-0.008,1.482],[0.47,0.819],[1.177,-0.006],[0.479,-0.824],[0.008,-1.457],[-0.47,-0.819],[-1.186,0.007]],"v":[[-1.239,-25.347],[-1.968,-21.939],[-1.276,-18.487],[1.208,-17.268],[3.691,-18.514],[4.422,-21.974],[3.728,-25.374],[1.258,-26.593]],"c":true},"ix":2},"nm":"Path 22","mn":"ADBE Vector Shape - Group","hd":false},{"ind":22,"ty":"sh","ix":23,"ks":{"a":0,"k":{"i":[[-0.09,-0.516],[0.004,-0.737],[0.104,-0.517],[0.307,-0.315],[0.567,-0.003],[0.303,0.312],[0.099,0.516],[-0.004,0.762],[-0.096,0.509],[-0.298,0.315],[-0.576,0.003],[-0.295,-0.312]],"o":[[0.099,0.508],[-0.004,0.762],[-0.096,0.517],[-0.298,0.315],[-0.576,0.003],[-0.295,-0.312],[-0.09,-0.516],[0.004,-0.737],[0.104,-0.517],[0.307,-0.315],[0.567,-0.003],[0.303,0.312]],"v":[[3.136,-23.834],[3.278,-21.967],[3.115,-20.048],[2.512,-18.8],[1.213,-18.323],[-0.105,-18.786],[-0.696,-20.027],[-0.825,-21.945],[-0.675,-23.813],[-0.072,-25.061],[1.252,-25.539],[2.545,-25.076]],"c":true},"ix":2},"nm":"Path 23","mn":"ADBE Vector Shape - Group","hd":false},{"ind":23,"ty":"sh","ix":24,"ks":{"a":0,"k":{"i":[[0.349,-0.349],[0.003,-0.576],[-0.345,-0.345],[-0.542,0.003],[-0.349,0.341],[-0.003,0.584],[0.345,0.337],[0.542,-0.003]],"o":[[-0.349,0.341],[-0.003,0.584],[0.345,0.337],[0.542,-0.003],[0.349,-0.349],[0.003,-0.576],[-0.345,-0.345],[-0.542,0.003]],"v":[[6.296,-25.782],[5.768,-24.407],[6.281,-23.013],[7.612,-22.512],[8.949,-23.027],[9.477,-24.428],[8.964,-25.797],[7.633,-26.31]],"c":true},"ix":2},"nm":"Path 24","mn":"ADBE Vector Shape - Group","hd":false},{"ind":24,"ty":"sh","ix":25,"ks":{"a":0,"k":{"i":[[0,0],[0,0],[0,0],[0,0]],"o":[[0,0],[0,0],[0,0],[0,0]],"v":[[8.003,-17.306],[13.196,-26.201],[12.053,-26.195],[6.86,-17.299]],"c":true},"ix":2},"nm":"Path 25","mn":"ADBE Vector Shape - Group","hd":false},{"ind":25,"ty":"sh","ix":26,"ks":{"a":0,"k":{"i":[[-0.162,0.196],[-0.288,0.002],[-0.168,-0.202],[0.002,-0.39],[0.171,-0.213],[0.288,-0.002],[0.168,0.202],[-0.002,0.39]],"o":[[0.17,-0.204],[0.288,-0.002],[0.168,0.194],[-0.002,0.381],[-0.17,0.204],[-0.288,0.002],[-0.16,-0.202],[0.002,-0.39]],"v":[[6.941,-25.29],[7.629,-25.599],[8.313,-25.298],[8.562,-24.423],[8.304,-23.532],[7.616,-23.223],[6.932,-23.524],[6.695,-24.412]],"c":true},"ix":2},"nm":"Path 26","mn":"ADBE Vector Shape - Group","hd":false},{"ind":26,"ty":"sh","ix":27,"ks":{"a":0,"k":{"i":[[0.349,-0.349],[0.003,-0.584],[-0.345,-0.345],[-0.542,0.003],[-0.341,0.349],[-0.003,0.576],[0.345,0.337],[0.542,-0.003]],"o":[[-0.349,0.341],[-0.003,0.584],[0.345,0.337],[0.542,-0.003],[0.349,-0.349],[0.003,-0.584],[-0.337,-0.345],[-0.542,0.003]],"v":[[11.133,-20.461],[10.604,-19.073],[11.118,-17.678],[12.449,-17.178],[13.773,-17.706],[14.301,-19.093],[13.788,-20.475],[12.469,-20.989]],"c":true},"ix":2},"nm":"Path 27","mn":"ADBE Vector Shape - Group","hd":false},{"ind":27,"ty":"sh","ix":28,"ks":{"a":0,"k":{"i":[[-0.17,0.196],[-0.288,0.002],[-0.168,-0.202],[0.002,-0.39],[0.17,-0.204],[0.288,-0.002],[0.168,0.194],[-0.002,0.381]],"o":[[0.17,-0.204],[0.288,-0.002],[0.168,0.194],[-0.002,0.381],[-0.17,0.196],[-0.288,0.002],[-0.168,-0.202],[0.002,-0.39]],"v":[[11.765,-19.956],[12.453,-20.265],[13.137,-19.963],[13.386,-19.088],[13.128,-18.21],[12.44,-17.914],[11.756,-18.203],[11.506,-19.078]],"c":true},"ix":2},"nm":"Path 28","mn":"ADBE Vector Shape - Group","hd":false},{"ind":28,"ty":"sh","ix":29,"ks":{"a":0,"k":{"i":[[-0.252,-0.354],[-0.473,-0.184],[0.307,-0.408],[0.003,-0.567],[-0.269,-0.413],[-0.482,-0.226],[-0.644,0.004],[-0.492,0.223],[-0.273,0.408],[-0.003,0.55],[0.311,0.396],[0.524,0.158],[-0.265,0.366],[-0.003,0.491],[0.235,0.363],[0.456,0.209],[0.644,-0.004],[0.459,-0.223],[0.231,-0.374],[0.002,-0.457]],"o":[[0.252,0.354],[-0.526,0.155],[-0.307,0.408],[-0.003,0.55],[0.269,0.405],[0.49,0.217],[0.644,-0.004],[0.501,-0.231],[0.273,-0.416],[0.003,-0.567],[-0.303,-0.405],[0.458,-0.18],[0.265,-0.374],[0.002,-0.457],[-0.227,-0.371],[-0.448,-0.218],[-0.644,0.004],[-0.45,0.214],[-0.231,0.365],[-0.003,0.508]],"v":[[-9.393,-65.559],[-8.305,-64.752],[-9.555,-63.907],[-10.02,-62.443],[-9.621,-60.997],[-8.496,-60.051],[-6.795,-59.73],[-5.091,-60.069],[-3.93,-61.029],[-3.516,-62.479],[-3.978,-63.925],[-5.218,-64.769],[-4.134,-65.588],[-3.733,-66.886],[-4.082,-68.116],[-5.107,-68.987],[-6.744,-69.308],[-8.397,-68.969],[-9.418,-68.087],[-9.768,-66.853]],"c":true},"ix":2},"nm":"Path 29","mn":"ADBE Vector Shape - Group","hd":false},{"ind":29,"ty":"sh","ix":30,"ks":{"a":0,"k":{"i":[[-0.337,-0.278],[0.003,-0.517],[0.357,-0.298],[0.567,-0.003],[0.354,0.286],[-0.003,0.474],[-0.34,0.281],[-0.584,0.003]],"o":[[0.337,0.278],[-0.003,0.474],[-0.349,0.29],[-0.559,0.003],[-0.346,-0.286],[0.003,-0.525],[0.34,-0.281],[0.593,-0.003]],"v":[[-5.354,-67.931],[-4.852,-66.74],[-5.392,-65.581],[-6.766,-65.142],[-8.136,-65.566],[-8.651,-66.706],[-8.136,-67.916],[-6.749,-68.343]],"c":true},"ix":2},"nm":"Path 30","mn":"ADBE Vector Shape - Group","hd":false},{"ind":30,"ty":"sh","ix":31,"ks":{"a":0,"k":{"i":[[-0.4,0.29],[-0.627,0.003],[-0.388,-0.303],[0.003,-0.567],[0.383,-0.332],[0.652,-0.004],[0.388,0.328],[-0.003,0.542]],"o":[[0.4,-0.299],[0.635,-0.003],[0.388,0.294],[-0.003,0.542],[-0.383,0.332],[-0.652,0.004],[-0.379,-0.328],[0.003,-0.584]],"v":[[-8.311,-63.799],[-6.771,-64.252],[-5.236,-63.803],[-4.659,-62.511],[-5.238,-61.199],[-6.79,-60.695],[-8.35,-61.182],[-8.915,-62.488]],"c":true},"ix":2},"nm":"Path 31","mn":"ADBE Vector Shape - Group","hd":false},{"ind":31,"ty":"sh","ix":32,"ks":{"a":0,"k":{"i":[[0.479,-0.824],[0.008,-1.457],[-0.47,-0.819],[-1.186,0.007],[-0.479,0.824],[-0.008,1.482],[0.47,0.81],[1.177,-0.006]],"o":[[-0.479,0.816],[-0.008,1.482],[0.47,0.819],[1.177,-0.006],[0.479,-0.824],[0.008,-1.457],[-0.47,-0.819],[-1.186,0.007]],"v":[[-1.239,-68.106],[-1.968,-64.698],[-1.276,-61.246],[1.208,-60.028],[3.691,-61.274],[4.422,-64.733],[3.728,-68.134],[1.258,-69.352]],"c":true},"ix":2},"nm":"Path 32","mn":"ADBE Vector Shape - Group","hd":false},{"ind":32,"ty":"sh","ix":33,"ks":{"a":0,"k":{"i":[[-0.09,-0.516],[0.004,-0.737],[0.104,-0.517],[0.307,-0.315],[0.567,-0.003],[0.303,0.312],[0.099,0.516],[-0.004,0.762],[-0.096,0.509],[-0.298,0.315],[-0.576,0.003],[-0.295,-0.312]],"o":[[0.099,0.508],[-0.004,0.762],[-0.096,0.517],[-0.298,0.315],[-0.576,0.003],[-0.295,-0.312],[-0.09,-0.516],[0.004,-0.737],[0.104,-0.517],[0.307,-0.315],[0.567,-0.003],[0.303,0.312]],"v":[[3.136,-66.593],[3.278,-64.727],[3.115,-62.808],[2.512,-61.559],[1.213,-61.082],[-0.105,-61.545],[-0.696,-62.787],[-0.825,-64.704],[-0.675,-66.572],[-0.072,-67.821],[1.252,-68.298],[2.545,-67.835]],"c":true},"ix":2},"nm":"Path 33","mn":"ADBE Vector Shape - Group","hd":false},{"ind":33,"ty":"sh","ix":34,"ks":{"a":0,"k":{"i":[[0.349,-0.349],[0.003,-0.576],[-0.345,-0.345],[-0.542,0.003],[-0.349,0.341],[-0.003,0.584],[0.345,0.337],[0.542,-0.003]],"o":[[-0.349,0.341],[-0.003,0.584],[0.345,0.337],[0.542,-0.003],[0.349,-0.349],[0.003,-0.576],[-0.345,-0.345],[-0.542,0.003]],"v":[[6.296,-68.542],[5.768,-67.167],[6.281,-65.772],[7.612,-65.271],[8.949,-65.787],[9.477,-67.187],[8.964,-68.556],[7.633,-69.07]],"c":true},"ix":2},"nm":"Path 34","mn":"ADBE Vector Shape - Group","hd":false},{"ind":34,"ty":"sh","ix":35,"ks":{"a":0,"k":{"i":[[0,0],[0,0],[0,0],[0,0]],"o":[[0,0],[0,0],[0,0],[0,0]],"v":[[8.003,-60.065],[13.196,-68.961],[12.053,-68.954],[6.86,-60.059]],"c":true},"ix":2},"nm":"Path 35","mn":"ADBE Vector Shape - Group","hd":false},{"ind":35,"ty":"sh","ix":36,"ks":{"a":0,"k":{"i":[[-0.162,0.196],[-0.288,0.002],[-0.168,-0.202],[0.002,-0.39],[0.171,-0.213],[0.288,-0.002],[0.168,0.202],[-0.002,0.39]],"o":[[0.17,-0.204],[0.288,-0.002],[0.168,0.194],[-0.002,0.381],[-0.17,0.204],[-0.288,0.002],[-0.16,-0.202],[0.002,-0.39]],"v":[[6.941,-68.05],[7.629,-68.358],[8.313,-68.057],[8.562,-67.182],[8.304,-66.291],[7.616,-65.983],[6.932,-66.284],[6.695,-67.172]],"c":true},"ix":2},"nm":"Path 36","mn":"ADBE Vector Shape - Group","hd":false},{"ind":36,"ty":"sh","ix":37,"ks":{"a":0,"k":{"i":[[0.349,-0.349],[0.003,-0.584],[-0.345,-0.345],[-0.542,0.003],[-0.341,0.349],[-0.003,0.576],[0.345,0.337],[0.542,-0.003]],"o":[[-0.349,0.341],[-0.003,0.584],[0.345,0.337],[0.542,-0.003],[0.349,-0.349],[0.003,-0.584],[-0.337,-0.345],[-0.542,0.003]],"v":[[11.133,-63.22],[10.604,-61.832],[11.118,-60.438],[12.449,-59.937],[13.773,-60.465],[14.301,-61.853],[13.788,-63.235],[12.469,-63.748]],"c":true},"ix":2},"nm":"Path 37","mn":"ADBE Vector Shape - Group","hd":false},{"ind":37,"ty":"sh","ix":38,"ks":{"a":0,"k":{"i":[[-0.17,0.196],[-0.288,0.002],[-0.168,-0.202],[0.002,-0.39],[0.17,-0.204],[0.288,-0.002],[0.168,0.194],[-0.002,0.381]],"o":[[0.17,-0.204],[0.288,-0.002],[0.168,0.194],[-0.002,0.381],[-0.17,0.196],[-0.288,0.002],[-0.168,-0.202],[0.002,-0.39]],"v":[[11.765,-62.715],[12.453,-63.024],[13.137,-62.723],[13.386,-61.848],[13.128,-60.97],[12.44,-60.674],[11.756,-60.962],[11.506,-61.837]],"c":true},"ix":2},"nm":"Path 38","mn":"ADBE Vector Shape - Group","hd":false},{"ind":38,"ty":"sh","ix":39,"ks":{"a":0,"k":{"i":[[0,0],[0,0],[0,0],[0,0],[0,0],[0,0]],"o":[[0,0],[0,0],[0,0],[0,0],[0,0],[0,0]],"v":[[-14.295,-110.726],[-14.301,-109.671],[-13.082,-109.678],[-13.125,-101.548],[-11.957,-101.554],[-11.907,-110.739]],"c":true},"ix":2},"nm":"Path 39","mn":"ADBE Vector Shape - Group","hd":false},{"ind":39,"ty":"sh","ix":40,"ks":{"a":0,"k":{"i":[[0.479,-0.824],[0.008,-1.457],[-0.47,-0.819],[-1.186,0.007],[-0.479,0.824],[-0.008,1.482],[0.47,0.81],[1.177,-0.006]],"o":[[-0.479,0.816],[-0.008,1.482],[0.47,0.819],[1.177,-0.006],[0.479,-0.824],[0.008,-1.457],[-0.47,-0.819],[-1.186,0.007]],"v":[[-9.216,-109.661],[-9.946,-106.253],[-9.253,-102.801],[-6.77,-101.583],[-4.286,-102.829],[-3.556,-106.288],[-4.249,-109.689],[-6.719,-110.907]],"c":true},"ix":2},"nm":"Path 40","mn":"ADBE Vector Shape - Group","hd":false},{"ind":40,"ty":"sh","ix":41,"ks":{"a":0,"k":{"i":[[-0.09,-0.516],[0.004,-0.737],[0.104,-0.517],[0.307,-0.315],[0.567,-0.003],[0.303,0.312],[0.099,0.516],[-0.004,0.762],[-0.096,0.509],[-0.298,0.315],[-0.576,0.003],[-0.295,-0.312]],"o":[[0.099,0.508],[-0.004,0.762],[-0.096,0.517],[-0.298,0.315],[-0.576,0.003],[-0.295,-0.312],[-0.09,-0.516],[0.004,-0.737],[0.104,-0.517],[0.307,-0.315],[0.567,-0.003],[0.303,0.312]],"v":[[-4.841,-108.148],[-4.699,-106.282],[-4.862,-104.362],[-5.466,-103.114],[-6.764,-102.637],[-8.083,-103.1],[-8.673,-104.342],[-8.802,-106.259],[-8.652,-108.127],[-8.049,-109.376],[-6.725,-109.853],[-5.432,-109.39]],"c":true},"ix":2},"nm":"Path 41","mn":"ADBE Vector Shape - Group","hd":false},{"ind":41,"ty":"sh","ix":42,"ks":{"a":0,"k":{"i":[[0.479,-0.824],[0.008,-1.457],[-0.47,-0.819],[-1.186,0.007],[-0.479,0.824],[-0.008,1.482],[0.47,0.81],[1.177,-0.006]],"o":[[-0.479,0.816],[-0.008,1.482],[0.47,0.819],[1.177,-0.006],[0.479,-0.824],[0.008,-1.457],[-0.47,-0.819],[-1.186,0.007]],"v":[[-1.239,-109.705],[-1.969,-106.297],[-1.276,-102.845],[1.208,-101.626],[3.691,-102.872],[4.421,-106.332],[3.728,-109.732],[1.258,-110.951]],"c":true},"ix":2},"nm":"Path 42","mn":"ADBE Vector Shape - Group","hd":false},{"ind":42,"ty":"sh","ix":43,"ks":{"a":0,"k":{"i":[[-0.09,-0.516],[0.004,-0.737],[0.104,-0.517],[0.307,-0.315],[0.567,-0.003],[0.303,0.312],[0.099,0.516],[-0.004,0.762],[-0.096,0.509],[-0.298,0.315],[-0.576,0.003],[-0.295,-0.312]],"o":[[0.099,0.508],[-0.004,0.762],[-0.096,0.517],[-0.298,0.315],[-0.576,0.003],[-0.295,-0.312],[-0.09,-0.516],[0.004,-0.737],[0.104,-0.517],[0.307,-0.315],[0.567,-0.003],[0.303,0.312]],"v":[[3.136,-108.192],[3.278,-106.325],[3.115,-104.406],[2.512,-103.158],[1.213,-102.681],[-0.105,-103.144],[-0.696,-104.385],[-0.825,-106.303],[-0.675,-108.171],[-0.072,-109.419],[1.252,-109.897],[2.545,-109.434]],"c":true},"ix":2},"nm":"Path 43","mn":"ADBE Vector Shape - Group","hd":false},{"ind":43,"ty":"sh","ix":44,"ks":{"a":0,"k":{"i":[[0.349,-0.349],[0.003,-0.576],[-0.345,-0.345],[-0.542,0.003],[-0.349,0.341],[-0.003,0.584],[0.345,0.337],[0.542,-0.003]],"o":[[-0.349,0.341],[-0.003,0.584],[0.345,0.337],[0.542,-0.003],[0.349,-0.349],[0.003,-0.576],[-0.345,-0.345],[-0.542,0.003]],"v":[[6.296,-110.14],[5.768,-108.765],[6.281,-107.371],[7.612,-106.87],[8.949,-107.385],[9.477,-108.786],[8.964,-110.155],[7.633,-110.668]],"c":true},"ix":2},"nm":"Path 44","mn":"ADBE Vector Shape - Group","hd":false},{"ind":44,"ty":"sh","ix":45,"ks":{"a":0,"k":{"i":[[0,0],[0,0],[0,0],[0,0]],"o":[[0,0],[0,0],[0,0],[0,0]],"v":[[8.003,-101.664],[13.196,-110.559],[12.053,-110.553],[6.86,-101.657]],"c":true},"ix":2},"nm":"Path 45","mn":"ADBE Vector Shape - Group","hd":false},{"ind":45,"ty":"sh","ix":46,"ks":{"a":0,"k":{"i":[[-0.162,0.196],[-0.288,0.002],[-0.168,-0.202],[0.002,-0.39],[0.171,-0.213],[0.288,-0.002],[0.168,0.202],[-0.002,0.39]],"o":[[0.17,-0.204],[0.288,-0.002],[0.168,0.194],[-0.002,0.381],[-0.17,0.204],[-0.288,0.002],[-0.16,-0.202],[0.002,-0.39]],"v":[[6.941,-109.648],[7.629,-109.957],[8.313,-109.656],[8.562,-108.781],[8.303,-107.89],[7.616,-107.581],[6.931,-107.882],[6.695,-108.77]],"c":true},"ix":2},"nm":"Path 46","mn":"ADBE Vector Shape - Group","hd":false},{"ind":46,"ty":"sh","ix":47,"ks":{"a":0,"k":{"i":[[0.349,-0.349],[0.003,-0.584],[-0.345,-0.345],[-0.542,0.003],[-0.341,0.349],[-0.003,0.576],[0.345,0.337],[0.542,-0.003]],"o":[[-0.349,0.341],[-0.003,0.584],[0.345,0.337],[0.542,-0.003],[0.349,-0.349],[0.003,-0.584],[-0.337,-0.345],[-0.542,0.003]],"v":[[11.132,-104.819],[10.604,-103.431],[11.117,-102.036],[12.449,-101.536],[13.773,-102.064],[14.301,-103.451],[13.788,-104.833],[12.469,-105.347]],"c":true},"ix":2},"nm":"Path 47","mn":"ADBE Vector Shape - Group","hd":false},{"ind":47,"ty":"sh","ix":48,"ks":{"a":0,"k":{"i":[[-0.17,0.196],[-0.288,0.002],[-0.168,-0.202],[0.002,-0.39],[0.17,-0.204],[0.288,-0.002],[0.168,0.194],[-0.002,0.381]],"o":[[0.17,-0.204],[0.288,-0.002],[0.168,0.194],[-0.002,0.381],[-0.17,0.196],[-0.288,0.002],[-0.168,-0.202],[0.002,-0.39]],"v":[[11.765,-104.314],[12.453,-104.623],[13.137,-104.321],[13.386,-103.446],[13.127,-102.568],[12.44,-102.272],[11.755,-102.561],[11.506,-103.436]],"c":true},"ix":2},"nm":"Path 48","mn":"ADBE Vector Shape - Group","hd":false},{"ty":"mm","mm":1,"nm":"Merge Paths 1","mn":"ADBE Vector Filter - Merge","hd":false},{"ty":"fl","c":{"a":0,"k":[0.600000023842,0.600000023842,0.600000023842,1],"ix":4},"o":{"a":0,"k":100,"ix":5},"r":1,"bm":0,"nm":"Fill 1","mn":"ADBE Vector Graphic - Fill","hd":false},{"ty":"tr","p":{"a":0,"k":[0,0],"ix":2},"a":{"a":0,"k":[0,0],"ix":1},"s":{"a":0,"k":[100,100],"ix":3},"r":{"a":0,"k":0,"ix":6},"o":{"a":0,"k":100,"ix":7},"sk":{"a":0,"k":0,"ix":4},"sa":{"a":0,"k":0,"ix":5},"nm":"Transform"}],"nm":"Vector","np":50,"cix":2,"bm":0,"ix":1,"mn":"ADBE Vector Group","hd":false}],"ip":0,"op":60,"st":0,"bm":0},{"ddd":0,"ind":13,"ty":4,"nm":"Vector","sr":1,"ks":{"o":{"a":0,"k":100,"ix":11},"r":{"a":0,"k":0,"ix":10},"p":{"a":0,"k":[194.71,303.611,0],"ix":2},"a":{"a":0,"k":[0,0,0],"ix":1},"s":{"a":0,"k":[100,100,100],"ix":6}},"ao":0,"shapes":[{"ty":"gr","it":[{"ind":0,"ty":"sh","ix":1,"ks":{"a":0,"k":{"i":[[0.483,-0.821],[0.016,-1.457],[-0.465,-0.821],[-1.186,0],[-0.483,0.821],[-0.016,1.482],[0.465,0.813],[1.177,0]],"o":[[-0.483,0.813],[-0.016,1.482],[0.465,0.821],[1.177,0],[0.483,-0.821],[0.016,-1.457],[-0.465,-0.821],[-1.186,0]],"v":[[-58.098,-3.748],[-58.846,-0.343],[-58.172,3.112],[-55.696,4.344],[-53.205,3.112],[-52.456,-0.343],[-53.131,-3.748],[-55.594,-4.98]],"c":true},"ix":2},"nm":"Path 1","mn":"ADBE Vector Shape - Group","hd":false},{"ind":1,"ty":"sh","ix":2,"ks":{"a":0,"k":{"i":[[-0.088,-0.517],[0.008,-0.737],[0.107,-0.517],[0.308,-0.313],[0.567,0],[0.301,0.313],[0.096,0.517],[-0.008,0.762],[-0.099,0.508],[-0.3,0.313],[-0.576,0],[-0.293,-0.313]],"o":[[0.096,0.508],[-0.008,0.762],[-0.099,0.517],[-0.3,0.313],[-0.576,0],[-0.293,-0.313],[-0.088,-0.517],[0.008,-0.737],[0.107,-0.517],[0.308,-0.313],[0.567,0],[0.301,0.313]],"v":[[-53.732,-2.211],[-53.6,-0.343],[-53.773,1.575],[-54.384,2.82],[-55.684,3.29],[-57.001,2.82],[-57.584,1.575],[-57.703,-0.343],[-57.543,-2.211],[-56.932,-3.455],[-55.606,-3.925],[-54.315,-3.455]],"c":true},"ix":2},"nm":"Path 2","mn":"ADBE Vector Shape - Group","hd":false},{"ind":2,"ty":"sh","ix":3,"ks":{"a":0,"k":{"i":[[0,0],[0,0],[0,0],[0,0],[0,0],[0,0],[-0.333,0.212],[-0.449,0],[-0.335,-0.364],[0.007,-0.661],[0.343,-0.406],[0.669,0],[0.353,0.271],[0.105,0.483],[0,0],[-0.546,-0.457],[-0.889,0],[-0.469,0.279],[-0.234,0.483],[-0.007,0.61],[0.19,0.457],[0.437,0.288],[0.703,0],[0.383,-0.178],[0.198,-0.271]],"o":[[0,0],[0,0],[0,0],[0,0],[0,0],[0.157,-0.373],[0.341,-0.22],[0.661,0],[0.335,0.356],[-0.007,0.661],[-0.343,0.398],[-0.542,0],[-0.353,-0.271],[0,0],[0.11,0.762],[0.546,0.457],[0.694,0],[0.477,-0.279],[0.234,-0.483],[0.006,-0.517],[-0.181,-0.466],[-0.437,-0.296],[-0.44,0],[-0.383,0.169],[0,0]],"v":[[-49.434,-3.837],[-44.975,-3.837],[-44.963,-4.853],[-50.49,-4.853],[-50.546,0.33],[-49.454,0.33],[-48.72,-0.546],[-47.535,-0.877],[-46.042,-0.33],[-45.55,1.194],[-46.076,2.795],[-47.594,3.392],[-48.936,2.985],[-49.623,1.855],[-50.753,1.855],[-49.77,3.684],[-47.617,4.37],[-45.872,3.951],[-44.806,2.807],[-44.445,1.169],[-44.721,-0.292],[-45.649,-1.423],[-47.359,-1.868],[-48.594,-1.601],[-49.465,-0.94]],"c":true},"ix":2},"nm":"Path 3","mn":"ADBE Vector Shape - Group","hd":false},{"ind":3,"ty":"sh","ix":4,"ks":{"a":0,"k":{"i":[[0,0],[0,0],[0,0],[0,0]],"o":[[0,0],[0,0],[0,0],[0,0]],"v":[[-41.937,6.504],[-38.303,-7.622],[-39.459,-7.622],[-43.081,6.504]],"c":true},"ix":2},"nm":"Path 4","mn":"ADBE Vector Shape - Group","hd":false},{"ind":4,"ty":"sh","ix":5,"ks":{"a":0,"k":{"i":[[0.483,-0.821],[0.016,-1.457],[-0.465,-0.821],[-1.186,0],[-0.483,0.821],[-0.016,1.482],[0.465,0.813],[1.177,0]],"o":[[-0.483,0.813],[-0.016,1.482],[0.465,0.821],[1.177,0],[0.483,-0.821],[0.016,-1.457],[-0.465,-0.821],[-1.186,0]],"v":[[-36.102,-3.748],[-36.85,-0.343],[-36.176,3.112],[-33.7,4.344],[-31.209,3.112],[-30.46,-0.343],[-31.134,-3.748],[-33.598,-4.98]],"c":true},"ix":2},"nm":"Path 5","mn":"ADBE Vector Shape - Group","hd":false},{"ind":5,"ty":"sh","ix":6,"ks":{"a":0,"k":{"i":[[-0.088,-0.517],[0.008,-0.737],[0.107,-0.517],[0.308,-0.313],[0.567,0],[0.301,0.313],[0.096,0.517],[-0.008,0.762],[-0.099,0.508],[-0.3,0.313],[-0.576,0],[-0.293,-0.313]],"o":[[0.096,0.508],[-0.008,0.762],[-0.099,0.517],[-0.3,0.313],[-0.576,0],[-0.293,-0.313],[-0.088,-0.517],[0.008,-0.737],[0.107,-0.517],[0.308,-0.313],[0.567,0],[0.301,0.313]],"v":[[-31.735,-2.211],[-31.603,-0.343],[-31.777,1.575],[-32.387,2.82],[-33.688,3.29],[-35.004,2.82],[-35.588,1.575],[-35.707,-0.343],[-35.547,-2.211],[-34.936,-3.455],[-33.61,-3.925],[-32.319,-3.455]],"c":true},"ix":2},"nm":"Path 6","mn":"ADBE Vector Shape - Group","hd":false},{"ind":6,"ty":"sh","ix":7,"ks":{"a":0,"k":{"i":[[0,0],[0,0],[0,0],[0,0],[0,0],[0,0],[-0.333,0.212],[-0.449,0],[-0.335,-0.364],[0.007,-0.661],[0.343,-0.406],[0.669,0],[0.353,0.271],[0.105,0.483],[0,0],[-0.546,-0.457],[-0.889,0],[-0.469,0.279],[-0.234,0.483],[-0.007,0.61],[0.19,0.457],[0.437,0.288],[0.703,0],[0.383,-0.178],[0.198,-0.271]],"o":[[0,0],[0,0],[0,0],[0,0],[0,0],[0.157,-0.373],[0.341,-0.22],[0.661,0],[0.335,0.356],[-0.007,0.661],[-0.343,0.398],[-0.542,0],[-0.353,-0.271],[0,0],[0.11,0.762],[0.546,0.457],[0.694,0],[0.477,-0.279],[0.234,-0.483],[0.006,-0.517],[-0.181,-0.466],[-0.437,-0.296],[-0.44,0],[-0.383,0.169],[0,0]],"v":[[-27.437,-3.837],[-22.978,-3.837],[-22.967,-4.853],[-28.493,-4.853],[-28.55,0.33],[-27.457,0.33],[-26.724,-0.546],[-25.539,-0.877],[-24.046,-0.33],[-23.554,1.194],[-24.08,2.795],[-25.598,3.392],[-26.94,2.985],[-27.626,1.855],[-28.757,1.855],[-27.773,3.684],[-25.621,4.37],[-23.876,3.951],[-22.809,2.807],[-22.448,1.169],[-22.725,-0.292],[-23.653,-1.423],[-25.363,-1.868],[-26.598,-1.601],[-27.469,-0.94]],"c":true},"ix":2},"nm":"Path 7","mn":"ADBE Vector Shape - Group","hd":false},{"ind":7,"ty":"sh","ix":8,"ks":{"a":0,"k":{"i":[[-0.004,0.339],[0,0],[0,0],[0,0],[0,0],[0,0],[0,0],[0,0],[0,0],[0,0],[0,0],[0,0],[-0.319,-0.296],[-0.644,0],[0,0],[0,0],[0,0],[0.143,0.135]],"o":[[0,0],[0,0],[0,0],[0,0],[0,0],[0,0],[0,0],[0,0],[0,0],[0,0],[0,0],[-0.007,0.678],[0.319,0.296],[0,0],[0,0],[0,0],[-0.356,0],[-0.142,-0.144]],"v":[[-135.785,2.439],[-135.74,-1.664],[-133.923,-1.664],[-133.913,-2.617],[-135.73,-2.617],[-135.71,-4.37],[-136.866,-4.37],[-136.886,-2.617],[-137.788,-2.617],[-137.798,-1.664],[-136.896,-1.664],[-136.941,2.439],[-136.474,3.9],[-135.03,4.345],[-133.989,4.345],[-133.978,3.367],[-134.829,3.367],[-135.577,3.163]],"c":true},"ix":2},"nm":"Path 8","mn":"ADBE Vector Shape - Group","hd":false},{"ind":8,"ty":"sh","ix":9,"ks":{"a":0,"k":{"i":[[-0.522,-0.296],[-0.652,0],[-0.545,0.296],[-0.319,0.542],[-0.008,0.72],[0.307,0.542],[0.53,0.288],[0.661,0],[0.537,-0.296],[0.319,-0.55],[0.008,-0.711],[-0.29,-0.55]],"o":[[0.53,0.296],[0.661,0],[0.545,-0.296],[0.328,-0.55],[0.008,-0.72],[-0.299,-0.542],[-0.53,-0.296],[-0.661,0],[-0.537,0.288],[-0.311,0.542],[-0.008,0.72],[0.299,0.542]],"v":[[-131.327,4.014],[-129.553,4.459],[-127.744,4.014],[-126.447,2.757],[-125.944,0.851],[-126.393,-1.042],[-127.637,-2.286],[-129.424,-2.731],[-131.22,-2.286],[-132.504,-1.029],[-132.982,0.851],[-132.558,2.757]],"c":true},"ix":2},"nm":"Path 9","mn":"ADBE Vector Shape - Group","hd":false},{"ind":9,"ty":"sh","ix":10,"ks":{"a":0,"k":{"i":[[0.366,-0.195],[0.415,0],[0.345,0.186],[0.207,0.39],[-0.006,0.567],[-0.216,0.39],[-0.349,0.186],[-0.423,0],[-0.354,-0.195],[-0.216,-0.39],[0.006,-0.559],[0.233,-0.39]],"o":[[-0.366,0.195],[-0.415,0],[-0.345,-0.195],[-0.199,-0.39],[0.006,-0.559],[0.216,-0.39],[0.358,-0.195],[0.415,0],[0.354,0.186],[0.216,0.39],[-0.006,0.559],[-0.224,0.39]],"v":[[-128.37,3.151],[-129.542,3.443],[-130.682,3.163],[-131.511,2.287],[-131.8,0.851],[-131.467,-0.571],[-130.619,-1.435],[-129.447,-1.727],[-128.295,-1.435],[-127.44,-0.571],[-127.125,0.851],[-127.484,2.274]],"c":true},"ix":2},"nm":"Path 10","mn":"ADBE Vector Shape - Group","hd":false},{"ind":10,"ty":"sh","ix":11,"ks":{"a":0,"k":{"i":[[0.294,-0.542],[0.008,-0.711],[-0.282,-0.55],[-0.496,-0.305],[-0.618,0],[-0.452,0.263],[-0.233,0.415],[0,0],[0,0],[0,0],[0,0],[0,0],[0.463,0.246],[0.542,0],[0.511,-0.296]],"o":[[-0.294,0.534],[-0.008,0.703],[0.282,0.55],[0.505,0.305],[0.601,0],[0.452,-0.271],[0,0],[0,0],[0,0],[0,0],[0,0],[-0.241,-0.406],[-0.463,-0.254],[-0.627,0],[-0.503,0.296]],"v":[[-124.403,-1.029],[-124.856,0.839],[-124.444,2.719],[-123.277,4.002],[-121.592,4.459],[-120.013,4.065],[-118.985,3.036],[-118.999,4.345],[-117.83,4.345],[-117.728,-5.056],[-118.897,-5.056],[-118.937,-1.372],[-119.993,-2.35],[-121.501,-2.731],[-123.208,-2.286]],"c":true},"ix":2},"nm":"Path 11","mn":"ADBE Vector Shape - Group","hd":false},{"ind":11,"ty":"sh","ix":12,"ks":{"a":0,"k":{"i":[[-0.207,-0.39],[0.006,-0.525],[0.216,-0.398],[0.366,-0.212],[0.432,0],[0.354,0.203],[0.207,0.39],[-0.006,0.534],[-0.216,0.39],[-0.358,0.203],[-0.432,0],[-0.353,-0.212]],"o":[[0.207,0.39],[-0.006,0.525],[-0.216,0.39],[-0.358,0.203],[-0.432,0],[-0.353,-0.212],[-0.207,-0.398],[0.006,-0.525],[0.216,-0.39],[0.358,-0.203],[0.432,0],[0.362,0.203]],"v":[[-119.264,-0.521],[-118.961,0.851],[-119.294,2.236],[-120.168,3.138],[-121.352,3.443],[-122.53,3.138],[-123.372,2.236],[-123.674,0.839],[-123.342,-0.533],[-122.481,-1.423],[-121.296,-1.727],[-120.118,-1.41]],"c":true},"ix":2},"nm":"Path 12","mn":"ADBE Vector Shape - Group","hd":false},{"ind":12,"ty":"sh","ix":13,"ks":{"a":0,"k":{"i":[[0.294,-0.542],[0.008,-0.711],[-0.282,-0.55],[-0.496,-0.305],[-0.618,0],[-0.452,0.263],[-0.233,0.406],[0,0],[0,0],[0,0],[0,0],[0,0],[0.446,0.263],[0.61,0],[0.511,-0.296]],"o":[[-0.294,0.534],[-0.008,0.703],[0.282,0.55],[0.496,0.305],[0.601,0],[0.46,-0.271],[0,0],[0,0],[0,0],[0,0],[0,0],[-0.216,-0.398],[-0.446,-0.263],[-0.618,0],[-0.503,0.296]],"v":[[-115.818,-1.029],[-116.271,0.839],[-115.859,2.719],[-114.692,4.002],[-113.02,4.459],[-111.44,4.065],[-110.4,3.049],[-110.414,4.345],[-109.245,4.345],[-109.17,-2.617],[-110.338,-2.617],[-110.352,-1.346],[-111.345,-2.337],[-112.929,-2.731],[-114.623,-2.286]],"c":true},"ix":2},"nm":"Path 13","mn":"ADBE Vector Shape - Group","hd":false},{"ind":13,"ty":"sh","ix":14,"ks":{"a":0,"k":{"i":[[-0.207,-0.39],[0.006,-0.525],[0.216,-0.398],[0.366,-0.212],[0.432,0],[0.354,0.203],[0.207,0.39],[-0.006,0.534],[-0.216,0.39],[-0.358,0.203],[-0.432,0],[-0.353,-0.212]],"o":[[0.207,0.39],[-0.006,0.525],[-0.216,0.39],[-0.358,0.203],[-0.432,0],[-0.353,-0.212],[-0.207,-0.398],[0.006,-0.525],[0.216,-0.39],[0.358,-0.203],[0.432,0],[0.362,0.203]],"v":[[-110.679,-0.521],[-110.376,0.851],[-110.709,2.236],[-111.582,3.138],[-112.767,3.443],[-113.945,3.138],[-114.787,2.236],[-115.089,0.839],[-114.757,-0.533],[-113.896,-1.423],[-112.711,-1.727],[-111.533,-1.41]],"c":true},"ix":2},"nm":"Path 14","mn":"ADBE Vector Shape - Group","hd":false},{"ind":14,"ty":"sh","ix":15,"ks":{"a":0,"k":{"i":[[0,0],[0,0],[0,0],[0,0],[0,0],[0,0],[0,0],[0,0]],"o":[[0,0],[0,0],[0,0],[0,0],[0,0],[0,0],[0,0],[0,0]],"v":[[-105.524,7.622],[-101.22,-2.617],[-102.414,-2.617],[-104.635,3.024],[-106.759,-2.617],[-108.042,-2.617],[-105.309,4.268],[-106.718,7.622]],"c":true},"ix":2},"nm":"Path 15","mn":"ADBE Vector Shape - Group","hd":false},{"ind":15,"ty":"sh","ix":16,"ks":{"a":0,"k":{"i":[[0.483,-0.821],[0.016,-1.457],[-0.465,-0.821],[-1.186,0],[-0.483,0.821],[-0.016,1.482],[0.465,0.813],[1.177,0]],"o":[[-0.483,0.813],[-0.016,1.482],[0.465,0.821],[1.177,0],[0.483,-0.821],[0.016,-1.457],[-0.465,-0.821],[-1.186,0]],"v":[[102.062,-3.748],[101.313,-0.343],[101.987,3.112],[104.463,4.344],[106.954,3.112],[107.703,-0.343],[107.029,-3.748],[104.565,-4.98]],"c":true},"ix":2},"nm":"Path 16","mn":"ADBE Vector Shape - Group","hd":false},{"ind":16,"ty":"sh","ix":17,"ks":{"a":0,"k":{"i":[[-0.088,-0.517],[0.008,-0.737],[0.107,-0.517],[0.308,-0.313],[0.567,0],[0.301,0.313],[0.096,0.517],[-0.008,0.762],[-0.099,0.508],[-0.3,0.313],[-0.576,0],[-0.293,-0.313]],"o":[[0.096,0.508],[-0.008,0.762],[-0.099,0.517],[-0.3,0.313],[-0.576,0],[-0.293,-0.313],[-0.088,-0.517],[0.008,-0.737],[0.107,-0.517],[0.308,-0.313],[0.567,0],[0.301,0.313]],"v":[[106.428,-2.211],[106.56,-0.343],[106.386,1.575],[105.776,2.82],[104.475,3.29],[103.159,2.82],[102.575,1.575],[102.456,-0.343],[102.617,-2.211],[103.227,-3.455],[104.553,-3.925],[105.844,-3.455]],"c":true},"ix":2},"nm":"Path 17","mn":"ADBE Vector Shape - Group","hd":false},{"ind":17,"ty":"sh","ix":18,"ks":{"a":0,"k":{"i":[[-0.754,0],[-0.176,-0.94],[0,0],[0.469,0.449],[0.83,0],[0.034,-3.108],[-0.187,-0.686],[-0.487,-0.39],[-0.872,0],[-0.452,0.271],[-0.225,0.457],[-0.006,0.576],[0.519,0.542],[0.872,0],[0.46,-0.254],[0.2,-0.44],[-0.379,0.576]],"o":[[0.974,0],[0,0],[-0.077,-0.686],[-0.469,-0.449],[-2.168,0],[-0.011,1.008],[0.187,0.686],[0.487,0.39],[0.644,0],[0.46,-0.271],[0.234,-0.457],[0.01,-0.957],[-0.511,-0.542],[-0.559,0],[-0.452,0.246],[0.006,-1.33],[0.379,-0.584]],"v":[[112.71,-4.065],[114.435,-2.655],[115.502,-2.655],[114.682,-4.357],[112.733,-5.031],[109.43,-0.369],[109.695,2.172],[110.706,3.785],[112.745,4.37],[114.388,3.963],[115.417,2.871],[115.777,1.321],[115.013,-0.927],[112.939,-1.74],[111.41,-1.359],[110.433,-0.33],[111.011,-3.189]],"c":true},"ix":2},"nm":"Path 18","mn":"ADBE Vector Shape - Group","hd":false},{"ind":18,"ty":"sh","ix":19,"ks":{"a":0,"k":{"i":[[-0.323,0.144],[-0.364,0],[-0.335,-0.381],[0.007,-0.661],[0.36,-0.373],[0.593,0],[0.368,0.398],[-0.007,0.644],[-0.198,0.296]],"o":[[0.323,-0.152],[0.652,0],[0.335,0.373],[-0.007,0.627],[-0.351,0.364],[-0.694,0],[-0.368,-0.406],[0.005,-0.432],[0.207,-0.305]],"v":[[111.655,-0.534],[112.687,-0.762],[114.167,-0.191],[114.658,1.359],[114.108,2.858],[112.692,3.404],[111.098,2.807],[110.556,1.232],[110.86,0.14]],"c":true},"ix":2},"nm":"Path 19","mn":"ADBE Vector Shape - Group","hd":false},{"ind":19,"ty":"sh","ix":20,"ks":{"a":0,"k":{"i":[[0,0],[0,0],[0,0],[0,0]],"o":[[0,0],[0,0],[0,0],[0,0]],"v":[[118.309,6.504],[121.943,-7.622],[120.787,-7.622],[117.165,6.504]],"c":true},"ix":2},"nm":"Path 20","mn":"ADBE Vector Shape - Group","hd":false},{"ind":20,"ty":"sh","ix":21,"ks":{"a":0,"k":{"i":[[0.483,-0.821],[0.016,-1.457],[-0.465,-0.821],[-1.186,0],[-0.483,0.821],[-0.016,1.482],[0.465,0.813],[1.177,0]],"o":[[-0.483,0.813],[-0.016,1.482],[0.465,0.821],[1.177,0],[0.483,-0.821],[0.016,-1.457],[-0.465,-0.821],[-1.186,0]],"v":[[124.145,-3.748],[123.396,-0.343],[124.07,3.112],[126.546,4.344],[129.037,3.112],[129.786,-0.343],[129.112,-3.748],[126.648,-4.98]],"c":true},"ix":2},"nm":"Path 21","mn":"ADBE Vector Shape - Group","hd":false},{"ind":21,"ty":"sh","ix":22,"ks":{"a":0,"k":{"i":[[-0.088,-0.517],[0.008,-0.737],[0.107,-0.517],[0.308,-0.313],[0.567,0],[0.301,0.313],[0.096,0.517],[-0.008,0.762],[-0.099,0.508],[-0.3,0.313],[-0.576,0],[-0.293,-0.313]],"o":[[0.096,0.508],[-0.008,0.762],[-0.099,0.517],[-0.3,0.313],[-0.576,0],[-0.293,-0.313],[-0.088,-0.517],[0.008,-0.737],[0.107,-0.517],[0.308,-0.313],[0.567,0],[0.301,0.313]],"v":[[128.511,-2.211],[128.643,-0.343],[128.469,1.575],[127.859,2.82],[126.558,3.29],[125.242,2.82],[124.658,1.575],[124.539,-0.343],[124.7,-2.211],[125.31,-3.455],[126.636,-3.925],[127.927,-3.455]],"c":true},"ix":2},"nm":"Path 22","mn":"ADBE Vector Shape - Group","hd":false},{"ind":22,"ty":"sh","ix":23,"ks":{"a":0,"k":{"i":[[0,0],[0,0],[0,0],[0,0],[0,0],[0,0],[-0.333,0.212],[-0.449,0],[-0.335,-0.364],[0.007,-0.661],[0.343,-0.406],[0.669,0],[0.353,0.271],[0.105,0.483],[0,0],[-0.546,-0.457],[-0.889,0],[-0.469,0.279],[-0.234,0.483],[-0.007,0.61],[0.19,0.457],[0.437,0.288],[0.703,0],[0.383,-0.178],[0.198,-0.271]],"o":[[0,0],[0,0],[0,0],[0,0],[0,0],[0.157,-0.373],[0.341,-0.22],[0.661,0],[0.335,0.356],[-0.007,0.661],[-0.343,0.398],[-0.542,0],[-0.353,-0.271],[0,0],[0.11,0.762],[0.546,0.457],[0.694,0],[0.477,-0.279],[0.234,-0.483],[0.006,-0.517],[-0.181,-0.466],[-0.437,-0.296],[-0.44,0],[-0.383,0.169],[0,0]],"v":[[132.809,-3.837],[137.268,-3.837],[137.279,-4.853],[131.753,-4.853],[131.696,0.33],[132.789,0.33],[133.522,-0.546],[134.708,-0.877],[136.201,-0.33],[136.692,1.194],[136.167,2.795],[134.648,3.392],[133.306,2.985],[132.62,1.855],[131.489,1.855],[132.473,3.684],[134.625,4.37],[136.37,3.951],[137.437,2.807],[137.798,1.169],[137.521,-0.292],[136.594,-1.423],[134.883,-1.868],[133.648,-1.601],[132.777,-0.94]],"c":true},"ix":2},"nm":"Path 23","mn":"ADBE Vector Shape - Group","hd":false},{"ind":23,"ty":"sh","ix":24,"ks":{"a":0,"k":{"i":[[0.483,-0.821],[0.016,-1.457],[-0.465,-0.821],[-1.186,0],[-0.483,0.821],[-0.016,1.482],[0.465,0.813],[1.177,0]],"o":[[-0.483,0.813],[-0.016,1.482],[0.465,0.821],[1.177,0],[0.483,-0.821],[0.016,-1.457],[-0.465,-0.821],[-1.186,0]],"v":[[22.338,-3.748],[21.59,-0.343],[22.264,3.112],[24.74,4.344],[27.231,3.112],[27.98,-0.343],[27.306,-3.748],[24.842,-4.98]],"c":true},"ix":2},"nm":"Path 24","mn":"ADBE Vector Shape - Group","hd":false},{"ind":24,"ty":"sh","ix":25,"ks":{"a":0,"k":{"i":[[-0.088,-0.517],[0.008,-0.737],[0.107,-0.517],[0.308,-0.313],[0.567,0],[0.301,0.313],[0.096,0.517],[-0.008,0.762],[-0.099,0.508],[-0.3,0.313],[-0.576,0],[-0.293,-0.313]],"o":[[0.096,0.508],[-0.008,0.762],[-0.099,0.517],[-0.3,0.313],[-0.576,0],[-0.293,-0.313],[-0.088,-0.517],[0.008,-0.737],[0.107,-0.517],[0.308,-0.313],[0.567,0],[0.301,0.313]],"v":[[26.705,-2.211],[26.837,-0.343],[26.663,1.575],[26.053,2.82],[24.752,3.29],[23.436,2.82],[22.852,1.575],[22.733,-0.343],[22.893,-2.211],[23.504,-3.455],[24.83,-3.925],[26.121,-3.455]],"c":true},"ix":2},"nm":"Path 25","mn":"ADBE Vector Shape - Group","hd":false},{"ind":25,"ty":"sh","ix":26,"ks":{"a":0,"k":{"i":[[0,0],[0,0],[0,0],[0,0],[0,0],[0,0],[-0.333,0.212],[-0.449,0],[-0.335,-0.364],[0.007,-0.661],[0.343,-0.406],[0.669,0],[0.353,0.271],[0.105,0.483],[0,0],[-0.546,-0.457],[-0.889,0],[-0.469,0.279],[-0.234,0.483],[-0.007,0.61],[0.19,0.457],[0.437,0.288],[0.703,0],[0.383,-0.178],[0.198,-0.271]],"o":[[0,0],[0,0],[0,0],[0,0],[0,0],[0.157,-0.373],[0.341,-0.22],[0.661,0],[0.335,0.356],[-0.007,0.661],[-0.343,0.398],[-0.542,0],[-0.353,-0.271],[0,0],[0.11,0.762],[0.546,0.457],[0.694,0],[0.477,-0.279],[0.234,-0.483],[0.006,-0.517],[-0.181,-0.466],[-0.437,-0.296],[-0.44,0],[-0.383,0.169],[0,0]],"v":[[31.003,-3.837],[35.462,-3.837],[35.473,-4.853],[29.947,-4.853],[29.89,0.33],[30.983,0.33],[31.716,-0.546],[32.901,-0.877],[34.394,-0.33],[34.886,1.194],[34.36,2.795],[32.842,3.392],[31.5,2.985],[30.814,1.855],[29.683,1.855],[30.667,3.684],[32.819,4.37],[34.564,3.951],[35.631,2.807],[35.992,1.169],[35.715,-0.292],[34.787,-1.423],[33.077,-1.868],[31.842,-1.601],[30.971,-0.94]],"c":true},"ix":2},"nm":"Path 26","mn":"ADBE Vector Shape - Group","hd":false},{"ind":26,"ty":"sh","ix":27,"ks":{"a":0,"k":{"i":[[0,0],[0,0],[0,0],[0,0]],"o":[[0,0],[0,0],[0,0],[0,0]],"v":[[38.499,6.504],[42.133,-7.622],[40.977,-7.622],[37.355,6.504]],"c":true},"ix":2},"nm":"Path 27","mn":"ADBE Vector Shape - Group","hd":false},{"ind":27,"ty":"sh","ix":28,"ks":{"a":0,"k":{"i":[[0.616,-0.559],[1.085,-0.864],[0,0],[0,0],[0,0],[0,0],[-0.539,0.5],[-0.422,0.661],[-0.008,0.703],[0.511,0.483],[0.872,0],[0.548,-0.517],[0.044,-0.949],[0,0],[-0.317,0.356],[-0.576,0],[-0.259,-0.322],[0.006,-0.55],[0.43,-0.61]],"o":[[-0.616,0.55],[0,0],[0,0],[0,0],[0,0],[0.837,-0.669],[0.539,-0.508],[0.431,-0.669],[0.009,-0.847],[-0.503,-0.483],[-0.855,0],[-0.548,0.517],[0,0],[0.032,-0.601],[0.326,-0.364],[0.593,0],[0.268,0.313],[-0.006,0.584],[-0.422,0.601]],"v":[[45.957,1.296],[43.405,3.417],[43.396,4.243],[49.507,4.243],[49.517,3.277],[45.147,3.277],[47.212,1.524],[48.654,-0.229],[49.311,-2.287],[48.558,-4.281],[46.495,-5.005],[44.391,-4.23],[43.503,-2.033],[44.621,-2.033],[45.145,-3.468],[46.497,-4.014],[47.775,-3.532],[48.167,-2.236],[47.513,-0.445]],"c":true},"ix":2},"nm":"Path 28","mn":"ADBE Vector Shape - Group","hd":false},{"ind":28,"ty":"sh","ix":29,"ks":{"a":0,"k":{"i":[[0.483,-0.821],[0.016,-1.457],[-0.465,-0.821],[-1.186,0],[-0.483,0.821],[-0.016,1.482],[0.465,0.813],[1.177,0]],"o":[[-0.483,0.813],[-0.016,1.482],[0.465,0.821],[1.177,0],[0.483,-0.821],[0.016,-1.457],[-0.465,-0.821],[-1.186,0]],"v":[[51.642,-3.748],[50.893,-0.343],[51.567,3.112],[54.044,4.344],[56.534,3.112],[57.283,-0.343],[56.609,-3.748],[54.145,-4.98]],"c":true},"ix":2},"nm":"Path 29","mn":"ADBE Vector Shape - Group","hd":false},{"ind":29,"ty":"sh","ix":30,"ks":{"a":0,"k":{"i":[[-0.088,-0.517],[0.008,-0.737],[0.107,-0.517],[0.308,-0.313],[0.567,0],[0.301,0.313],[0.096,0.517],[-0.008,0.762],[-0.099,0.508],[-0.3,0.313],[-0.576,0],[-0.293,-0.313]],"o":[[0.096,0.508],[-0.008,0.762],[-0.099,0.517],[-0.3,0.313],[-0.576,0],[-0.293,-0.313],[-0.088,-0.517],[0.008,-0.737],[0.107,-0.517],[0.308,-0.313],[0.567,0],[0.301,0.313]],"v":[[56.008,-2.211],[56.14,-0.343],[55.967,1.575],[55.356,2.82],[54.055,3.29],[52.739,2.82],[52.156,1.575],[52.037,-0.343],[52.197,-2.211],[52.807,-3.455],[54.134,-3.925],[55.424,-3.455]],"c":true},"ix":2},"nm":"Path 30","mn":"ADBE Vector Shape - Group","hd":false},{"ty":"mm","mm":1,"nm":"Merge Paths 1","mn":"ADBE Vector Filter - Merge","hd":false},{"ty":"fl","c":{"a":0,"k":[0.600000023842,0.600000023842,0.600000023842,1],"ix":4},"o":{"a":0,"k":100,"ix":5},"r":1,"bm":0,"nm":"Fill 1","mn":"ADBE Vector Graphic - Fill","hd":false},{"ty":"tr","p":{"a":0,"k":[0,0],"ix":2},"a":{"a":0,"k":[0,0],"ix":1},"s":{"a":0,"k":[100,100],"ix":3},"r":{"a":0,"k":0,"ix":6},"o":{"a":0,"k":100,"ix":7},"sk":{"a":0,"k":0,"ix":4},"sa":{"a":0,"k":0,"ix":5},"nm":"Transform"}],"nm":"Vector","np":32,"cix":2,"bm":0,"ix":1,"mn":"ADBE Vector Group","hd":false}],"ip":0,"op":60,"st":0,"bm":0},{"ddd":0,"ind":14,"ty":4,"nm":"most likely to pass","sr":1,"ks":{"o":{"a":0,"k":100,"ix":11},"r":{"a":0,"k":0,"ix":10},"p":{"a":0,"k":[290.662,116.952,0],"ix":2},"a":{"a":0,"k":[0,0,0],"ix":1},"s":{"a":1,"k":[{"i":{"x":[0.667,0.667,0.667],"y":[1,1,1]},"o":{"x":[0.333,0.333,0.333],"y":[0,0,0]},"t":45,"s":[0,0,100]},{"t":53,"s":[100,100,100]}],"ix":6}},"ao":0,"shapes":[{"ty":"gr","it":[{"ind":0,"ty":"sh","ix":1,"ks":{"a":0,"k":{"i":[[0.416,0.216],[0.52,0],[0.424,-0.24],[0.2,-0.4],[0.416,0.224],[0.528,0],[0.344,-0.152],[0.224,-0.272],[0,0],[0,0],[0,0],[0,0],[0,0],[-0.296,0.312],[-0.512,0],[-0.296,-0.32],[0,-0.592],[0,0],[0,0],[0,0],[-0.296,0.312],[-0.512,0],[-0.296,-0.32],[0,-0.592],[0,0],[0,0],[0,0],[0.24,0.424]],"o":[[-0.408,-0.216],[-0.488,0],[-0.424,0.232],[-0.224,-0.424],[-0.416,-0.224],[-0.392,0],[-0.344,0.152],[0,0],[0,0],[0,0],[0,0],[0,0],[0,-0.592],[0.304,-0.32],[0.512,0],[0.296,0.312],[0,0],[0,0],[0,0],[0,-0.592],[0.304,-0.32],[0.512,0],[0.296,0.312],[0,0],[0,0],[0,0],[0,-0.6],[-0.232,-0.424]],"v":[[-45.904,-3.348],[-47.296,-3.672],[-48.664,-3.312],[-49.6,-2.364],[-50.56,-3.336],[-51.976,-3.672],[-53.08,-3.444],[-53.932,-2.808],[-53.932,-3.564],[-55.3,-3.564],[-55.3,3.048],[-53.932,3.048],[-53.932,-0.648],[-53.488,-2.004],[-52.264,-2.484],[-51.052,-2.004],[-50.608,-0.648],[-50.608,3.048],[-49.252,3.048],[-49.252,-0.648],[-48.808,-2.004],[-47.584,-2.484],[-46.372,-2.004],[-45.928,-0.648],[-45.928,3.048],[-44.572,3.048],[-44.572,-0.852],[-44.932,-2.388]],"c":true},"ix":2},"nm":"Path 1","mn":"ADBE Vector Shape - Group","hd":false},{"ind":1,"ty":"sh","ix":2,"ks":{"a":0,"k":{"i":[[-0.504,-0.288],[-0.624,0],[-0.52,0.28],[-0.304,0.52],[0,0.672],[0.296,0.52],[0.512,0.28],[0.632,0],[0.512,-0.28],[0.296,-0.52],[0,-0.672],[-0.288,-0.52]],"o":[[0.504,0.28],[0.632,0],[0.528,-0.288],[0.304,-0.52],[0,-0.672],[-0.296,-0.52],[-0.512,-0.28],[-0.632,0],[-0.512,0.28],[-0.296,0.52],[0,0.68],[0.288,0.512]],"v":[[-41.655,2.736],[-39.963,3.156],[-38.235,2.736],[-36.987,1.524],[-36.531,-0.264],[-36.975,-2.052],[-38.187,-3.252],[-39.903,-3.672],[-41.619,-3.252],[-42.831,-2.052],[-43.275,-0.264],[-42.843,1.536]],"c":true},"ix":2},"nm":"Path 2","mn":"ADBE Vector Shape - Group","hd":false},{"ind":2,"ty":"sh","ix":3,"ks":{"a":0,"k":{"i":[[0.312,-0.168],[0.352,0],[0.368,0.384],[0,0.712],[-0.176,0.328],[-0.296,0.168],[-0.352,0],[-0.304,-0.168],[-0.184,-0.336],[0,-0.48],[0.192,-0.336]],"o":[[-0.304,0.168],[-0.552,0],[-0.36,-0.392],[0,-0.48],[0.176,-0.336],[0.304,-0.168],[0.352,0],[0.304,0.168],[0.184,0.328],[0,0.48],[-0.192,0.336]],"v":[[-38.979,1.716],[-39.963,1.968],[-41.343,1.392],[-41.883,-0.264],[-41.619,-1.476],[-40.911,-2.232],[-39.927,-2.484],[-38.943,-2.232],[-38.211,-1.476],[-37.935,-0.264],[-38.223,0.96]],"c":true},"ix":2},"nm":"Path 3","mn":"ADBE Vector Shape - Group","hd":false},{"ind":3,"ty":"sh","ix":4,"ks":{"a":0,"k":{"i":[[-0.408,-0.192],[-0.52,0],[-0.376,0.168],[-0.208,0.296],[0,0.376],[0.224,0.256],[0.312,0.128],[0.48,0.128],[0.184,0.064],[0.128,0.12],[0,0.176],[-0.192,0.136],[-0.36,0],[-0.216,-0.176],[-0.024,-0.296],[0,0],[0.464,0.376],[0.752,0],[0.392,-0.168],[0.208,-0.296],[0,-0.352],[-0.224,-0.264],[-0.312,-0.128],[-0.496,-0.136],[-0.232,-0.12],[0,-0.248],[0.216,-0.152],[0.384,0],[0.248,0.184],[0.024,0.28],[0,0],[-0.24,-0.328]],"o":[[0.416,0.184],[0.512,0],[0.384,-0.168],[0.208,-0.296],[-0.008,-0.424],[-0.224,-0.256],[-0.304,-0.136],[-0.36,-0.104],[-0.184,-0.072],[-0.128,-0.12],[0,-0.224],[0.192,-0.136],[0.368,0],[0.216,0.176],[0,0],[-0.032,-0.656],[-0.456,-0.384],[-0.504,0],[-0.384,0.168],[-0.208,0.288],[0,0.432],[0.232,0.264],[0.312,0.128],[0.512,0.144],[0.24,0.12],[0,0.232],[-0.208,0.144],[-0.368,0],[-0.24,-0.192],[0,0],[0.016,0.4],[0.24,0.32]],"v":[[-34.183,2.88],[-32.779,3.156],[-31.447,2.904],[-30.559,2.208],[-30.247,1.2],[-30.595,0.18],[-31.399,-0.396],[-32.575,-0.792],[-33.391,-1.044],[-33.859,-1.332],[-34.051,-1.776],[-33.763,-2.316],[-32.935,-2.52],[-32.059,-2.256],[-31.699,-1.548],[-30.331,-1.548],[-31.075,-3.096],[-32.887,-3.672],[-34.231,-3.42],[-35.119,-2.724],[-35.431,-1.764],[-35.095,-0.72],[-34.279,-0.132],[-33.067,0.264],[-31.951,0.66],[-31.591,1.212],[-31.915,1.788],[-32.803,2.004],[-33.727,1.728],[-34.123,1.02],[-35.539,1.02],[-35.155,2.112]],"c":true},"ix":2},"nm":"Path 4","mn":"ADBE Vector Shape - Group","hd":false},{"ind":4,"ty":"sh","ix":5,"ks":{"a":0,"k":{"i":[[0,0.248],[0,0],[0,0],[0,0],[0,0],[0,0],[0,0],[0,0],[0,0],[0,0],[0,0],[0,0],[-0.328,-0.288],[-0.616,0],[0,0],[0,0],[0,0],[0.12,0.104]],"o":[[0,0],[0,0],[0,0],[0,0],[0,0],[0,0],[0,0],[0,0],[0,0],[0,0],[0,0],[0,0.648],[0.328,0.288],[0,0],[0,0],[0,0],[-0.28,0],[-0.112,-0.112]],"v":[[-27.173,1.212],[-27.173,-2.448],[-25.565,-2.448],[-25.565,-3.564],[-27.173,-3.564],[-27.173,-5.208],[-28.553,-5.208],[-28.553,-3.564],[-29.333,-3.564],[-29.333,-2.448],[-28.553,-2.448],[-28.553,1.212],[-28.061,2.616],[-26.645,3.048],[-25.565,3.048],[-25.565,1.908],[-26.405,1.908],[-27.005,1.752]],"c":true},"ix":2},"nm":"Path 5","mn":"ADBE Vector Shape - Group","hd":false},{"ind":5,"ty":"sh","ix":6,"ks":{"a":0,"k":{"i":[[0,0],[0,0],[0,0],[0,0]],"o":[[0,0],[0,0],[0,0],[0,0]],"v":[[-19.819,3.048],[-19.819,-5.832],[-21.187,-5.832],[-21.187,3.048]],"c":true},"ix":2},"nm":"Path 6","mn":"ADBE Vector Shape - Group","hd":false},{"ind":6,"ty":"sh","ix":7,"ks":{"a":0,"k":{"i":[[-0.168,-0.168],[-0.248,0],[-0.168,0.168],[0,0.248],[0.168,0.168],[0.24,0],[0.168,-0.168],[0,-0.248]],"o":[[0.168,0.168],[0.24,0],[0.168,-0.168],[0,-0.248],[-0.168,-0.168],[-0.248,0],[-0.168,0.168],[0,0.248]],"v":[[-17.951,-4.692],[-17.327,-4.44],[-16.715,-4.692],[-16.463,-5.316],[-16.715,-5.94],[-17.327,-6.192],[-17.951,-5.94],[-18.203,-5.316]],"c":true},"ix":2},"nm":"Path 7","mn":"ADBE Vector Shape - Group","hd":false},{"ind":7,"ty":"sh","ix":8,"ks":{"a":0,"k":{"i":[[0,0],[0,0],[0,0],[0,0]],"o":[[0,0],[0,0],[0,0],[0,0]],"v":[[-16.655,3.048],[-16.655,-3.564],[-18.023,-3.564],[-18.023,3.048]],"c":true},"ix":2},"nm":"Path 8","mn":"ADBE Vector Shape - Group","hd":false},{"ind":8,"ty":"sh","ix":9,"ks":{"a":0,"k":{"i":[[0,0],[0,0],[0,0],[0,0],[0,0],[0,0],[0,0],[0,0],[0,0],[0,0],[0,0]],"o":[[0,0],[0,0],[0,0],[0,0],[0,0],[0,0],[0,0],[0,0],[0,0],[0,0],[0,0]],"v":[[-9.195,3.048],[-12.243,-0.252],[-9.195,-3.564],[-11.091,-3.564],[-13.491,-0.672],[-13.491,-5.832],[-14.859,-5.832],[-14.859,3.048],[-13.491,3.048],[-13.491,0.204],[-11.043,3.048]],"c":true},"ix":2},"nm":"Path 9","mn":"ADBE Vector Shape - Group","hd":false},{"ind":9,"ty":"sh","ix":10,"ks":{"a":0,"k":{"i":[[0,0],[0,0.248],[0.272,0.488],[0.488,0.272],[0.624,0],[0.504,-0.28],[0.28,-0.52],[0,-0.68],[-0.28,-0.52],[-0.496,-0.288],[-0.632,0],[-0.52,0.384],[-0.2,0.608],[0,0],[0.736,0],[0.352,0.32],[0.04,0.528]],"o":[[0.032,-0.2],[0,-0.64],[-0.272,-0.496],[-0.488,-0.272],[-0.648,0],[-0.496,0.28],[-0.272,0.512],[0,0.68],[0.288,0.512],[0.504,0.28],[0.776,0],[0.528,-0.392],[0,0],[-0.304,0.616],[-0.512,0],[-0.352,-0.32],[0,0]],"v":[[-2.202,0.252],[-2.154,-0.42],[-2.562,-2.112],[-3.702,-3.264],[-5.37,-3.672],[-7.098,-3.252],[-8.262,-2.052],[-8.67,-0.264],[-8.25,1.536],[-7.074,2.736],[-5.37,3.156],[-3.426,2.58],[-2.334,1.08],[-3.81,1.08],[-5.37,2.004],[-6.666,1.524],[-7.254,0.252]],"c":true},"ix":2},"nm":"Path 10","mn":"ADBE Vector Shape - Group","hd":false},{"ind":10,"ty":"sh","ix":11,"ks":{"a":0,"k":{"i":[[-0.352,-0.304],[-0.008,-0.504],[0,0],[-0.336,0.296],[-0.472,0]],"o":[[0.352,0.304],[0,0],[0.064,-0.512],[0.336,-0.304],[0.52,0]],"v":[[-4.122,-2.064],[-3.582,-0.852],[-7.242,-0.852],[-6.642,-2.064],[-5.43,-2.52]],"c":true},"ix":2},"nm":"Path 11","mn":"ADBE Vector Shape - Group","hd":false},{"ind":11,"ty":"sh","ix":12,"ks":{"a":0,"k":{"i":[[0,0],[0,0],[0,0],[0,0]],"o":[[0,0],[0,0],[0,0],[0,0]],"v":[[0.56,3.048],[0.56,-5.832],[-0.808,-5.832],[-0.808,3.048]],"c":true},"ix":2},"nm":"Path 12","mn":"ADBE Vector Shape - Group","hd":false},{"ind":12,"ty":"sh","ix":13,"ks":{"a":0,"k":{"i":[[0,0],[0,0],[0,0],[0,0],[0,0],[0,0],[0,0],[0,0]],"o":[[0,0],[0,0],[0,0],[0,0],[0,0],[0,0],[0,0],[0,0]],"v":[[4.252,6.156],[8.308,-3.564],[6.892,-3.564],[4.96,1.476],[3.1,-3.564],[1.576,-3.564],[4.18,2.94],[2.836,6.156]],"c":true},"ix":2},"nm":"Path 13","mn":"ADBE Vector Shape - Group","hd":false},{"ind":13,"ty":"sh","ix":14,"ks":{"a":0,"k":{"i":[[0,0.248],[0,0],[0,0],[0,0],[0,0],[0,0],[0,0],[0,0],[0,0],[0,0],[0,0],[0,0],[-0.328,-0.288],[-0.616,0],[0,0],[0,0],[0,0],[0.12,0.104]],"o":[[0,0],[0,0],[0,0],[0,0],[0,0],[0,0],[0,0],[0,0],[0,0],[0,0],[0,0],[0,0.648],[0.328,0.288],[0,0],[0,0],[0,0],[-0.28,0],[-0.112,-0.112]],"v":[[14.054,1.212],[14.054,-2.448],[15.662,-2.448],[15.662,-3.564],[14.054,-3.564],[14.054,-5.208],[12.674,-5.208],[12.674,-3.564],[11.894,-3.564],[11.894,-2.448],[12.674,-2.448],[12.674,1.212],[13.166,2.616],[14.582,3.048],[15.662,3.048],[15.662,1.908],[14.822,1.908],[14.222,1.752]],"c":true},"ix":2},"nm":"Path 14","mn":"ADBE Vector Shape - Group","hd":false},{"ind":14,"ty":"sh","ix":15,"ks":{"a":0,"k":{"i":[[-0.504,-0.288],[-0.624,0],[-0.52,0.28],[-0.304,0.52],[0,0.672],[0.296,0.52],[0.512,0.28],[0.632,0],[0.512,-0.28],[0.296,-0.52],[0,-0.672],[-0.288,-0.52]],"o":[[0.504,0.28],[0.632,0],[0.528,-0.288],[0.304,-0.52],[0,-0.672],[-0.296,-0.52],[-0.512,-0.28],[-0.632,0],[-0.512,0.28],[-0.296,0.52],[0,0.68],[0.288,0.512]],"v":[[18.099,2.736],[19.791,3.156],[21.519,2.736],[22.767,1.524],[23.223,-0.264],[22.779,-2.052],[21.567,-3.252],[19.851,-3.672],[18.135,-3.252],[16.923,-2.052],[16.479,-0.264],[16.911,1.536]],"c":true},"ix":2},"nm":"Path 15","mn":"ADBE Vector Shape - Group","hd":false},{"ind":15,"ty":"sh","ix":16,"ks":{"a":0,"k":{"i":[[0.312,-0.168],[0.352,0],[0.368,0.384],[0,0.712],[-0.176,0.328],[-0.296,0.168],[-0.352,0],[-0.304,-0.168],[-0.184,-0.336],[0,-0.48],[0.192,-0.336]],"o":[[-0.304,0.168],[-0.552,0],[-0.36,-0.392],[0,-0.48],[0.176,-0.336],[0.304,-0.168],[0.352,0],[0.304,0.168],[0.184,0.328],[0,0.48],[-0.192,0.336]],"v":[[20.775,1.716],[19.791,1.968],[18.411,1.392],[17.871,-0.264],[18.135,-1.476],[18.843,-2.232],[19.827,-2.484],[20.811,-2.232],[21.543,-1.476],[21.819,-0.264],[21.531,0.96]],"c":true},"ix":2},"nm":"Path 16","mn":"ADBE Vector Shape - Group","hd":false},{"ind":16,"ty":"sh","ix":17,"ks":{"a":0,"k":{"i":[[0.4,-0.208],[0.232,-0.304],[0,0],[0,0],[0,0],[0,0],[0,0],[-0.392,-0.208],[-0.504,0],[-0.472,0.288],[-0.272,0.52],[0,0.664],[0.272,0.512],[0.48,0.28],[0.576,0]],"o":[[-0.4,0.208],[0,0],[0,0],[0,0],[0,0],[0,0],[0.248,0.304],[0.392,0.2],[0.576,0],[0.48,-0.296],[0.272,-0.528],[0,-0.664],[-0.272,-0.512],[-0.472,-0.288],[-0.504,0]],"v":[[30.008,-3.36],[29.06,-2.592],[29.06,-3.564],[27.692,-3.564],[27.692,6.192],[29.06,6.192],[29.06,2.088],[30.02,2.856],[31.364,3.156],[32.936,2.724],[34.064,1.5],[34.472,-0.288],[34.064,-2.052],[32.936,-3.24],[31.364,-3.672]],"c":true},"ix":2},"nm":"Path 17","mn":"ADBE Vector Shape - Group","hd":false},{"ind":17,"ty":"sh","ix":18,"ks":{"a":0,"k":{"i":[[-0.184,-0.336],[0,-0.456],[0.192,-0.344],[0.312,-0.184],[0.352,0],[0.312,0.176],[0.192,0.336],[0,0.456],[-0.184,0.336],[-0.304,0.176],[-0.344,0],[-0.304,-0.176]],"o":[[0.192,0.328],[0,0.456],[-0.184,0.344],[-0.304,0.176],[-0.344,0],[-0.304,-0.176],[-0.184,-0.344],[0,-0.456],[0.192,-0.336],[0.312,-0.176],[0.352,0],[0.312,0.168]],"v":[[32.792,-1.464],[33.08,-0.288],[32.792,0.912],[32.048,1.704],[31.064,1.968],[30.08,1.704],[29.336,0.936],[29.06,-0.264],[29.336,-1.452],[30.08,-2.22],[31.064,-2.484],[32.048,-2.22]],"c":true},"ix":2},"nm":"Path 18","mn":"ADBE Vector Shape - Group","hd":false},{"ind":18,"ty":"sh","ix":19,"ks":{"a":0,"k":{"i":[[0.28,-0.512],[0,-0.664],[-0.272,-0.528],[-0.472,-0.296],[-0.568,0],[-0.4,0.208],[-0.232,0.312],[0,0],[0,0],[0,0],[0,0],[0,0],[0.392,0.2],[0.52,0],[0.48,-0.288]],"o":[[-0.272,0.512],[0,0.664],[0.28,0.52],[0.472,0.288],[0.512,0],[0.4,-0.208],[0,0],[0,0],[0,0],[0,0],[0,0],[-0.232,-0.304],[-0.384,-0.208],[-0.576,0],[-0.472,0.28]],"v":[[35.777,-2.052],[35.369,-0.288],[35.777,1.5],[36.905,2.724],[38.465,3.156],[39.833,2.844],[40.781,2.064],[40.781,3.048],[42.161,3.048],[42.161,-3.564],[40.781,-3.564],[40.781,-2.604],[39.845,-3.36],[38.489,-3.672],[36.905,-3.24]],"c":true},"ix":2},"nm":"Path 19","mn":"ADBE Vector Shape - Group","hd":false},{"ind":19,"ty":"sh","ix":20,"ks":{"a":0,"k":{"i":[[-0.184,-0.336],[0,-0.456],[0.192,-0.344],[0.304,-0.176],[0.352,0],[0.312,0.176],[0.192,0.344],[0,0.456],[-0.184,0.328],[-0.304,0.168],[-0.352,0],[-0.304,-0.176]],"o":[[0.192,0.336],[0,0.456],[-0.184,0.336],[-0.304,0.176],[-0.344,0],[-0.304,-0.184],[-0.184,-0.344],[0,-0.456],[0.192,-0.336],[0.304,-0.176],[0.352,0],[0.304,0.176]],"v":[[40.493,-1.452],[40.781,-0.264],[40.493,0.936],[39.761,1.704],[38.777,1.968],[37.793,1.704],[37.049,0.912],[36.773,-0.288],[37.049,-1.464],[37.793,-2.22],[38.777,-2.484],[39.761,-2.22]],"c":true},"ix":2},"nm":"Path 20","mn":"ADBE Vector Shape - Group","hd":false},{"ind":20,"ty":"sh","ix":21,"ks":{"a":0,"k":{"i":[[-0.408,-0.192],[-0.52,0],[-0.376,0.168],[-0.208,0.296],[0,0.376],[0.224,0.256],[0.312,0.128],[0.48,0.128],[0.184,0.064],[0.128,0.12],[0,0.176],[-0.192,0.136],[-0.36,0],[-0.216,-0.176],[-0.024,-0.296],[0,0],[0.464,0.376],[0.752,0],[0.392,-0.168],[0.208,-0.296],[0,-0.352],[-0.224,-0.264],[-0.312,-0.128],[-0.496,-0.136],[-0.232,-0.12],[0,-0.248],[0.216,-0.152],[0.384,0],[0.248,0.184],[0.024,0.28],[0,0],[-0.24,-0.328]],"o":[[0.416,0.184],[0.512,0],[0.384,-0.168],[0.208,-0.296],[-0.008,-0.424],[-0.224,-0.256],[-0.304,-0.136],[-0.36,-0.104],[-0.184,-0.072],[-0.128,-0.12],[0,-0.224],[0.192,-0.136],[0.368,0],[0.216,0.176],[0,0],[-0.032,-0.656],[-0.456,-0.384],[-0.504,0],[-0.384,0.168],[-0.208,0.288],[0,0.432],[0.232,0.264],[0.312,0.128],[0.512,0.144],[0.24,0.12],[0,0.232],[-0.208,0.144],[-0.368,0],[-0.24,-0.192],[0,0],[0.016,0.4],[0.24,0.32]],"v":[[44.954,2.88],[46.358,3.156],[47.69,2.904],[48.578,2.208],[48.89,1.2],[48.542,0.18],[47.738,-0.396],[46.562,-0.792],[45.746,-1.044],[45.278,-1.332],[45.086,-1.776],[45.374,-2.316],[46.202,-2.52],[47.078,-2.256],[47.438,-1.548],[48.806,-1.548],[48.062,-3.096],[46.25,-3.672],[44.906,-3.42],[44.018,-2.724],[43.706,-1.764],[44.042,-0.72],[44.858,-0.132],[46.07,0.264],[47.186,0.66],[47.546,1.212],[47.222,1.788],[46.334,2.004],[45.41,1.728],[45.014,1.02],[43.598,1.02],[43.982,2.112]],"c":true},"ix":2},"nm":"Path 21","mn":"ADBE Vector Shape - Group","hd":false},{"ind":21,"ty":"sh","ix":22,"ks":{"a":0,"k":{"i":[[-0.408,-0.192],[-0.52,0],[-0.376,0.168],[-0.208,0.296],[0,0.376],[0.224,0.256],[0.312,0.128],[0.48,0.128],[0.184,0.064],[0.128,0.12],[0,0.176],[-0.192,0.136],[-0.36,0],[-0.216,-0.176],[-0.024,-0.296],[0,0],[0.464,0.376],[0.752,0],[0.392,-0.168],[0.208,-0.296],[0,-0.352],[-0.224,-0.264],[-0.312,-0.128],[-0.496,-0.136],[-0.232,-0.12],[0,-0.248],[0.216,-0.152],[0.384,0],[0.248,0.184],[0.024,0.28],[0,0],[-0.24,-0.328]],"o":[[0.416,0.184],[0.512,0],[0.384,-0.168],[0.208,-0.296],[-0.008,-0.424],[-0.224,-0.256],[-0.304,-0.136],[-0.36,-0.104],[-0.184,-0.072],[-0.128,-0.12],[0,-0.224],[0.192,-0.136],[0.368,0],[0.216,0.176],[0,0],[-0.032,-0.656],[-0.456,-0.384],[-0.504,0],[-0.384,0.168],[-0.208,0.288],[0,0.432],[0.232,0.264],[0.312,0.128],[0.512,0.144],[0.24,0.12],[0,0.232],[-0.208,0.144],[-0.368,0],[-0.24,-0.192],[0,0],[0.016,0.4],[0.24,0.32]],"v":[[51.364,2.88],[52.768,3.156],[54.1,2.904],[54.988,2.208],[55.3,1.2],[54.952,0.18],[54.148,-0.396],[52.972,-0.792],[52.156,-1.044],[51.688,-1.332],[51.496,-1.776],[51.784,-2.316],[52.612,-2.52],[53.488,-2.256],[53.848,-1.548],[55.216,-1.548],[54.472,-3.096],[52.66,-3.672],[51.316,-3.42],[50.428,-2.724],[50.116,-1.764],[50.452,-0.72],[51.268,-0.132],[52.48,0.264],[53.596,0.66],[53.956,1.212],[53.632,1.788],[52.744,2.004],[51.82,1.728],[51.424,1.02],[50.008,1.02],[50.392,2.112]],"c":true},"ix":2},"nm":"Path 22","mn":"ADBE Vector Shape - Group","hd":false},{"ty":"mm","mm":1,"nm":"Merge Paths 1","mn":"ADBE Vector Filter - Merge","hd":false},{"ty":"fl","c":{"a":0,"k":[0.952941179276,0.57647061348,0.341176480055,1],"ix":4},"o":{"a":0,"k":100,"ix":5},"r":1,"bm":0,"nm":"Fill 1","mn":"ADBE Vector Graphic - Fill","hd":false},{"ty":"tr","p":{"a":0,"k":[0,0],"ix":2},"a":{"a":0,"k":[0,0],"ix":1},"s":{"a":0,"k":[100,100],"ix":3},"r":{"a":0,"k":0,"ix":6},"o":{"a":0,"k":100,"ix":7},"sk":{"a":0,"k":0,"ix":4},"sa":{"a":0,"k":0,"ix":5},"nm":"Transform"}],"nm":"most likely to pass","np":24,"cix":2,"bm":0,"ix":1,"mn":"ADBE Vector Group","hd":false}],"ip":0,"op":60,"st":0,"bm":0},{"ddd":0,"ind":15,"ty":4,"nm":"Line 28","sr":1,"ks":{"o":{"a":0,"k":100,"ix":11},"r":{"a":0,"k":0,"ix":10},"p":{"a":0,"k":[200.5,105,0],"ix":2},"a":{"a":0,"k":[0,0,0],"ix":1},"s":{"a":0,"k":[116.148,-111.673,100],"ix":6}},"ao":0,"shapes":[{"ty":"gr","it":[{"ind":0,"ty":"sh","ix":1,"ks":{"a":0,"k":{"i":[[0,0],[0,0]],"o":[[0,0],[0,0]],"v":[[-128.5,0],[128.5,0]],"c":false},"ix":2},"nm":"Path 1","mn":"ADBE Vector Shape - Group","hd":false},{"ty":"st","c":{"a":0,"k":[0.952941236309,0.576470588235,0.341176470588,1],"ix":3},"o":{"a":0,"k":100,"ix":4},"w":{"a":0,"k":1.15,"ix":5},"lc":1,"lj":1,"ml":4,"bm":0,"nm":"Stroke 1","mn":"ADBE Vector Graphic - Stroke","hd":false},{"ty":"tr","p":{"a":0,"k":[0,0],"ix":2},"a":{"a":0,"k":[0,0],"ix":1},"s":{"a":0,"k":[100,100],"ix":3},"r":{"a":0,"k":0,"ix":6},"o":{"a":0,"k":100,"ix":7},"sk":{"a":0,"k":0,"ix":4},"sa":{"a":0,"k":0,"ix":5},"nm":"Transform"}],"nm":"Line 28","np":2,"cix":2,"bm":0,"ix":1,"mn":"ADBE Vector Group","hd":false},{"ty":"tm","s":{"a":0,"k":0,"ix":1},"e":{"a":1,"k":[{"i":{"x":[0.351],"y":[1]},"o":{"x":[0.333],"y":[0]},"t":35,"s":[0]},{"t":45,"s":[100]}],"ix":2},"o":{"a":0,"k":0,"ix":3},"m":1,"ix":2,"nm":"Trim Paths 1","mn":"ADBE Vector Filter - Trim","hd":false}],"ip":0,"op":60,"st":0,"bm":0}],"markers":[]}